Workbook

Sheet cd_dashboard
A1: custom_region_name | B1: council_name | C1: contract_name | D1: contract_dno_regions | E1: work_package_name | F1: capex_bom | G1: capex_installation | H1: capex_connection | I1: target_sites | J1: target_sockets | K1: contingency_percent | L1: target_sockets_1 | M1: target_sockets_2 | N1: target_sockets_3 | O1: target_sockets_4 | P1: target_sockets_5 | Q1: target_sockets_6 | R1: target_sockets_7 | S1: target_sockets_8 | T1: target_sockets_9 | U1: target_sockets_10 | V1: target_sockets_11 | W1: target_sockets_12 | X1: planned_sites | Y1: planned_sockets_1 | Z1: planned_sockets_2 | AA1: planned_sockets_3 | AB1: planned_sockets_4 | AC1: planned_sockets_5 | AD1: planned_sockets_6 | AE1: planned_sockets_7 | AF1: planned_sockets_8 | AG1: planned_sockets_9 | AH1: planned_sockets_10 | AI1: planned_sockets_11 | AJ1: planned_sockets_12
A2: SOUTH | B2: Surrey | C2: Surrey | D2: UKPN_SE | E2: Surrey WP10 | F2: =J2*Assumption!$B$2 -> 150000 | G2: =J2*Assumption!$B$3 -> 150000 | H2: =J2*Assumption!$B$4 -> 150000 | I2: 10 | J2: =SUM(L2:W2) -> 150 | K2: 10 | L2: 50 | M2: 50 | N2: 50 | X2: =SUM(Y2:AJ2) -> 165 | Y2: =ROUND(L2*(100+$K2)/100,0) -> 55 | Z2: =ROUND(M2*(100+$K2)/100,0) -> 55 | AA2: =ROUND(N2*(100+$K2)/100,0) -> 55 | AB2: =ROUND(O2*(100+$K2)/100,0) -> 0 | AC2: =ROUND(P2*(100+$K2)/100,0) -> 0 | AD2: =ROUND(Q2*(100+$K2)/100,0) -> 0 | AE2: =ROUND(R2*(100+$K2)/100,0) -> 0 | AF2: =ROUND(S2*(100+$K2)/100,0) -> 0 | ... AJ2: =ROUND(W2*(100+$K2)/100,0) -> 0
A3: SOUTH | B3: Surrey | C3: Surrey | D3: UKPN_SE | E3: Surrey WP11 | F3: =J3*Assumption!$B$2 -> 100000 | G3: =J3*Assumption!$B$3 -> 100000 | H3: =J3*Assumption!$B$4 -> 100000 | I3: 10 | J3: =SUM(L3:W3) -> 100 | K3: 10 | P3: 50 | Q3: 50 | X3: =SUM(Y3:AJ3) -> 110 | Y3: =ROUND(L3*(100+$K3)/100,0) -> 0 | Z3: 0 | AA3: =ROUND(N3*(100+$K3)/100,0) -> 0 | AB3: =ROUND(O3*(100+$K3)/100,0) -> 0 | AC3: =ROUND(P3*(100+$K3)/100,0) -> 55 | AD3: =ROUND(Q3*(100+$K3)/100,0) -> 55 | AE3: =ROUND(R3*(100+$K3)/100,0) -> 0 | AF3: =ROUND(S3*(100+$K3)/100,0) -> 0 | AG3: =ROUND(T3*(100+$K3)/100,0) -> 0 | AH3: =ROUND(U3*(100+$K3)/100,0) -> 0 | ... AJ3: =ROUND(W3*(100+$K3)/100,0) -> 0
A4: SOUTH | B4: Surrey | C4: Surrey | D4: UKPN_SE | E4: Surrey WP12 | F4: =J4*Assumption!$B$2 -> 100000 | G4: =J4*Assumption!$B$3 -> 100000 | H4: =J4*Assumption!$B$4 -> 100000 | I4: 10 | J4: =SUM(L4:W4) -> 100 | K4: 10 | Q4: 50 | R4: 50 | X4: =SUM(Y4:AJ4) -> 110 | Y4: =ROUND(L4*(100+$K4)/100,0) -> 0 | Z4: 0 | AA4: =ROUND(N4*(100+$K4)/100,0) -> 0 | AB4: =ROUND(O4*(100+$K4)/100,0) -> 0 | AC4: =ROUND(P4*(100+$K4)/100,0) -> 0 | AD4: =ROUND(Q4*(100+$K4)/100,0) -> 55 | AE4: =ROUND(R4*(100+$K4)/100,0) -> 55 | AF4: =ROUND(S4*(100+$K4)/100,0) -> 0 | AG4: =ROUND(T4*(100+$K4)/100,0) -> 0 | AH4: =ROUND(U4*(100+$K4)/100,0) -> 0 | ... AJ4: =ROUND(W4*(100+$K4)/100,0) -> 0
A5: SOUTH | B5: Surrey | C5: Surrey | D5: UKPN_SE | E5: Surrey WP13 | F5: =J5*Assumption!$B$2 -> 100000 | G5: =J5*Assumption!$B$3 -> 100000 | H5: =J5*Assumption!$B$4 -> 100000 | I5: 10 | J5: =SUM(L5:W5) -> 100 | K5: 10 | R5: 50 | S5: 50 | X5: =SUM(Y5:AJ5) -> 110 | Y5: =ROUND(L5*(100+$K5)/100,0) -> 0 | Z5: 0 | AA5: =ROUND(N5*(100+$K5)/100,0) -> 0 | AB5: =ROUND(O5*(100+$K5)/100,0) -> 0 | AC5: =ROUND(P5*(100+$K5)/100,0) -> 0 | AD5: =ROUND(Q5*(100+$K5)/100,0) -> 0 | AE5: =ROUND(R5*(100+$K5)/100,0) -> 55 | AF5: =ROUND(S5*(100+$K5)/100,0) -> 55 | AG5: =ROUND(T5*(100+$K5)/100,0) -> 0 | AH5: =ROUND(U5*(100+$K5)/100,0) -> 0 | ... AJ5: =ROUND(W5*(100+$K5)/100,0) -> 0
A6: SOUTH | B6: Surrey | C6: Surrey | D6: UKPN_SE | E6: Surrey WP14 | F6: =J6*Assumption!$B$2 -> 100000 | G6: =J6*Assumption!$B$3 -> 100000 | H6: =J6*Assumption!$B$4 -> 100000 | I6: 10 | J6: =SUM(L6:W6) -> 100 | K6: 10 | S6: 50 | T6: 50 | X6: =SUM(Y6:AJ6) -> 110 | Y6: =ROUND(L6*(100+$K6)/100,0) -> 0 | Z6: 0 | AA6: =ROUND(N6*(100+$K6)/100,0) -> 0 | AB6: =ROUND(O6*(100+$K6)/100,0) -> 0 | AC6: =ROUND(P6*(100+$K6)/100,0) -> 0 | AD6: =ROUND(Q6*(100+$K6)/100,0) -> 0 | AE6: =ROUND(R6*(100+$K6)/100,0) -> 0 | AF6: =ROUND(S6*(100+$K6)/100,0) -> 55 | AG6: =ROUND(T6*(100+$K6)/100,0) -> 55 | AH6: =ROUND(U6*(100+$K6)/100,0) -> 0 | ... AJ6: =ROUND(W6*(100+$K6)/100,0) -> 0
A7: SOUTH | B7: Surrey | C7: Surrey | D7: UKPN_SE | E7: Surrey WP15 | F7: =J7*Assumption!$B$2 -> 100000 | G7: =J7*Assumption!$B$3 -> 100000 | H7: =J7*Assumption!$B$4 -> 100000 | I7: 10 | J7: =SUM(L7:W7) -> 100 | K7: 10 | U7: 50 | V7: 50 | X7: =SUM(Y7:AJ7) -> 110 | Y7: =ROUND(L7*(100+$K7)/100,0) -> 0 | Z7: 0 | AA7: =ROUND(N7*(100+$K7)/100,0) -> 0 | AB7: =ROUND(O7*(100+$K7)/100,0) -> 0 | AC7: =ROUND(P7*(100+$K7)/100,0) -> 0 | AD7: =ROUND(Q7*(100+$K7)/100,0) -> 0 | AE7: =ROUND(R7*(100+$K7)/100,0) -> 0 | AF7: =ROUND(S7*(100+$K7)/100,0) -> 0 | AG7: =ROUND(T7*(100+$K7)/100,0) -> 0 | AH7: =ROUND(U7*(100+$K7)/100,0) -> 55 | ... AJ7: =ROUND(W7*(100+$K7)/100,0) -> 0
A8: SOUTH | B8: Surrey | C8: Surrey | D8: UKPN_SE | E8: Surrey WP16 | F8: =J8*Assumption!$B$2 -> 50000 | G8: =J8*Assumption!$B$3 -> 50000 | H8: =J8*Assumption!$B$4 -> 50000 | I8: 10 | J8: =SUM(L8:W8) -> 50 | K8: 10 | W8: 50 | X8: =SUM(Y8:AJ8) -> 55 | Y8: =ROUND(L8*(100+$K8)/100,0) -> 0 | Z8: 0 | AA8: =ROUND(N8*(100+$K8)/100,0) -> 0 | AB8: =ROUND(O8*(100+$K8)/100,0) -> 0 | AC8: =ROUND(P8*(100+$K8)/100,0) -> 0 | AD8: =ROUND(Q8*(100+$K8)/100,0) -> 0 | AE8: =ROUND(R8*(100+$K8)/100,0) -> 0 | AF8: =ROUND(S8*(100+$K8)/100,0) -> 0 | AG8: =ROUND(T8*(100+$K8)/100,0) -> 0 | AH8: =ROUND(U8*(100+$K8)/100,0) -> 0 | ... AJ8: =ROUND(W8*(100+$K8)/100,0) -> 55
A9: SOUTH | B9: Surrey | C9: Surrey | D9: UKPN_SE | E9: Surrey WP17 | F9: =J9*Assumption!$B$2 -> 0 | G9: =J9*Assumption!$B$3 -> 0 | H9: =J9*Assumption!$B$4 -> 0 | I9: 10 | J9: =SUM(L9:W9) -> 0 | K9: 10 | X9: =SUM(Y9:AJ9) -> 0 | Y9: =ROUND(L9*(100+$K9)/100,0) -> 0 | Z9: 0 | AA9: =ROUND(N9*(100+$K9)/100,0) -> 0 | AB9: =ROUND(O9*(100+$K9)/100,0) -> 0 | AC9: =ROUND(P9*(100+$K9)/100,0) -> 0 | AD9: =ROUND(Q9*(100+$K9)/100,0) -> 0 | AE9: =ROUND(R9*(100+$K9)/100,0) -> 0 | AF9: =ROUND(S9*(100+$K9)/100,0) -> 0 | AG9: =ROUND(T9*(100+$K9)/100,0) -> 0 | AH9: =ROUND(U9*(100+$K9)/100,0) -> 0 | ... AJ9: =ROUND(W9*(100+$K9)/100,0) -> 0
A10: SOUTH | B10: Surrey | C10: Surrey | D10: UKPN_SE | E10: Surrey WP18 | F10: =J10*Assumption!$B$2 -> 0 | G10: =J10*Assumption!$B$3 -> 0 | H10: =J10*Assumption!$B$4 -> 0 | I10: 10 | J10: =SUM(L10:W10) -> 0 | K10: 10 | X10: =SUM(Y10:AJ10) -> 0 | Y10: =ROUND(L10*(100+$K10)/100,0) -> 0 | Z10: 0 | AA10: =ROUND(N10*(100+$K10)/100,0) -> 0 | AB10: =ROUND(O10*(100+$K10)/100,0) -> 0 | AC10: =ROUND(P10*(100+$K10)/100,0) -> 0 | AD10: =ROUND(Q10*(100+$K10)/100,0) -> 0 | AE10: =ROUND(R10*(100+$K10)/100,0) -> 0 | AF10: =ROUND(S10*(100+$K10)/100,0) -> 0 | AG10: =ROUND(T10*(100+$K10)/100,0) -> 0 | AH10: =ROUND(U10*(100+$K10)/100,0) -> 0 | ... AJ10: =ROUND(W10*(100+$K10)/100,0) -> 0
A11: SOUTH | B11: Surrey | C11: Surrey | D11: UKPN_SE | E11: Surrey WP19 | F11: =J11*Assumption!$B$2 -> 0 | G11: =J11*Assumption!$B$3 -> 0 | H11: =J11*Assumption!$B$4 -> 0 | I11: 10 | J11: =SUM(L11:W11) -> 0 | K11: 10 | X11: =SUM(Y11:AJ11) -> 0 | Y11: =ROUND(L11*(100+$K11)/100,0) -> 0 | Z11: 0 | AA11: =ROUND(N11*(100+$K11)/100,0) -> 0 | AB11: =ROUND(O11*(100+$K11)/100,0) -> 0 | AC11: =ROUND(P11*(100+$K11)/100,0) -> 0 | AD11: =ROUND(Q11*(100+$K11)/100,0) -> 0 | AE11: =ROUND(R11*(100+$K11)/100,0) -> 0 | AF11: =ROUND(S11*(100+$K11)/100,0) -> 0 | AG11: =ROUND(T11*(100+$K11)/100,0) -> 0 | AH11: =ROUND(U11*(100+$K11)/100,0) -> 0 | ... AJ11: =ROUND(W11*(100+$K11)/100,0) -> 0
A12: SOUTH | B12: Surrey | C12: Surrey | D12: UKPN_SE | E12: Surrey WP20 | F12: =J12*Assumption!$B$2 -> 0 | G12: =J12*Assumption!$B$3 -> 0 | H12: =J12*Assumption!$B$4 -> 0 | I12: 10 | J12: =SUM(L12:W12) -> 0 | K12: 10 | X12: =SUM(Y12:AJ12) -> 0 | Y12: =ROUND(L12*(100+$K12)/100,0) -> 0 | Z12: 0 | AA12: =ROUND(N12*(100+$K12)/100,0) -> 0 | AB12: =ROUND(O12*(100+$K12)/100,0) -> 0 | AC12: =ROUND(P12*(100+$K12)/100,0) -> 0 | AD12: =ROUND(Q12*(100+$K12)/100,0) -> 0 | AE12: =ROUND(R12*(100+$K12)/100,0) -> 0 | AF12: =ROUND(S12*(100+$K12)/100,0) -> 0 | AG12: =ROUND(T12*(100+$K12)/100,0) -> 0 | AH12: =ROUND(U12*(100+$K12)/100,0) -> 0 | ... AJ12: =ROUND(W12*(100+$K12)/100,0) -> 0
A13: SOUTH | B13: Surrey | C13: Surrey | D13: UKPN_SE | E13: Surrey WP21 | F13: =J13*Assumption!$B$2 -> 0 | G13: =J13*Assumption!$B$3 -> 0 | H13: =J13*Assumption!$B$4 -> 0 | I13: 10 | J13: =SUM(L13:W13) -> 0 | K13: 10 | X13: =SUM(Y13:AJ13) -> 0 | Y13: =ROUND(L13*(100+$K13)/100,0) -> 0 | Z13: 0 | AA13: =ROUND(N13*(100+$K13)/100,0) -> 0 | AB13: =ROUND(O13*(100+$K13)/100,0) -> 0 | AC13: =ROUND(P13*(100+$K13)/100,0) -> 0 | AD13: =ROUND(Q13*(100+$K13)/100,0) -> 0 | AE13: =ROUND(R13*(100+$K13)/100,0) -> 0 | AF13: =ROUND(S13*(100+$K13)/100,0) -> 0 | AG13: =ROUND(T13*(100+$K13)/100,0) -> 0 | AH13: =ROUND(U13*(100+$K13)/100,0) -> 0 | ... AJ13: =ROUND(W13*(100+$K13)/100,0) -> 0
A14: SOUTH | B14: Surrey | C14: Surrey | D14: UKPN_SE | E14: Surrey WP22 | F14: =J14*Assumption!$B$2 -> 0 | G14: =J14*Assumption!$B$3 -> 0 | H14: =J14*Assumption!$B$4 -> 0 | I14: 10 | J14: =SUM(L14:W14) -> 0 | K14: 10 | X14: =SUM(Y14:AJ14) -> 0 | Y14: =ROUND(L14*(100+$K14)/100,0) -> 0 | Z14: 0 | AA14: =ROUND(N14*(100+$K14)/100,0) -> 0 | AB14: =ROUND(O14*(100+$K14)/100,0) -> 0 | AC14: =ROUND(P14*(100+$K14)/100,0) -> 0 | AD14: =ROUND(Q14*(100+$K14)/100,0) -> 0 | AE14: =ROUND(R14*(100+$K14)/100,0) -> 0 | AF14: =ROUND(S14*(100+$K14)/100,0) -> 0 | AG14: =ROUND(T14*(100+$K14)/100,0) -> 0 | AH14: =ROUND(U14*(100+$K14)/100,0) -> 0 | ... AJ14: =ROUND(W14*(100+$K14)/100,0) -> 0
A15: SOUTH | B15: Surrey LP | C15: Surrey LP | D15: UKPN_SE | E15: Surrey Lamppost WP1 | F15: =J15*Assumption!$B$2 -> 100000 | G15: =J15*Assumption!$B$3 -> 100000 | H15: =J15*Assumption!$B$4 -> 100000 | I15: 10 | J15: =SUM(L15:W15) -> 100 | K15: 10 | O15: 50 | P15: 50 | X15: =SUM(Y15:AJ15) -> 110 | Y15: =ROUND(L15*(100+$K15)/100,0) -> 0 | Z15: 0 | AA15: =ROUND(N15*(100+$K15)/100,0) -> 0 | AB15: =ROUND(O15*(100+$K15)/100,0) -> 55 | AC15: =ROUND(P15*(100+$K15)/100,0) -> 55 | AD15: =ROUND(Q15*(100+$K15)/100,0) -> 0 | AE15: =ROUND(R15*(100+$K15)/100,0) -> 0 | AF15: =ROUND(S15*(100+$K15)/100,0) -> 0 | AG15: =ROUND(T15*(100+$K15)/100,0) -> 0 | AH15: =ROUND(U15*(100+$K15)/100,0) -> 0 | ... AJ15: =ROUND(W15*(100+$K15)/100,0) -> 0
A16: SOUTH | B16: Surrey LP | C16: Surrey LP | D16: UKPN_SE | E16: Surrey Lamppost WP2 | F16: =J16*Assumption!$B$2 -> 300000 | G16: =J16*Assumption!$B$3 -> 300000 | H16: =J16*Assumption!$B$4 -> 300000 | I16: 10 | J16: =SUM(L16:W16) -> 300 | K16: 10 | Q16: 50 | R16: 50 | S16: 50 | T16: 50 | U16: 50 | V16: 50 | X16: =SUM(Y16:AJ16) -> 330 | Y16: =ROUND(L16*(100+$K16)/100,0) -> 0 | Z16: 0 | AA16: =ROUND(N16*(100+$K16)/100,0) -> 0 | AB16: =ROUND(O16*(100+$K16)/100,0) -> 0 | AC16: =ROUND(P16*(100+$K16)/100,0) -> 0 | AD16: =ROUND(Q16*(100+$K16)/100,0) -> 55 | AE16: =ROUND(R16*(100+$K16)/100,0) -> 55 | AF16: =ROUND(S16*(100+$K16)/100,0) -> 55 | AG16: =ROUND(T16*(100+$K16)/100,0) -> 55 | AH16: =ROUND(U16*(100+$K16)/100,0) -> 55 | ... AJ16: =ROUND(W16*(100+$K16)/100,0) -> 0
A17: SOUTH | B17: Surrey LP | C17: Surrey LP | D17: UKPN_SE | E17: Surrey Lamppost WP3 | F17: =J17*Assumption!$B$2 -> 100000 | G17: =J17*Assumption!$B$3 -> 100000 | H17: =J17*Assumption!$B$4 -> 100000 | I17: 10 | J17: =SUM(L17:W17) -> 100 | K17: 10 | Q17: 50 | R17: 50 | X17: =SUM(Y17:AJ17) -> 110 | Y17: =ROUND(L17*(100+$K17)/100,0) -> 0 | Z17: 0 | AA17: =ROUND(N17*(100+$K17)/100,0) -> 0 | AB17: =ROUND(O17*(100+$K17)/100,0) -> 0 | AC17: =ROUND(P17*(100+$K17)/100,0) -> 0 | AD17: =ROUND(Q17*(100+$K17)/100,0) -> 55 | AE17: =ROUND(R17*(100+$K17)/100,0) -> 55 | AF17: =ROUND(S17*(100+$K17)/100,0) -> 0 | AG17: =ROUND(T17*(100+$K17)/100,0) -> 0 | AH17: =ROUND(U17*(100+$K17)/100,0) -> 0 | ... AJ17: =ROUND(W17*(100+$K17)/100,0) -> 0
A18: SOUTH | B18: Surrey LP | C18: Surrey LP | D18: UKPN_SE | E18: Surrey Lamppost WP4 | F18: =J18*Assumption!$B$2 -> 100000 | G18: =J18*Assumption!$B$3 -> 100000 | H18: =J18*Assumption!$B$4 -> 100000 | I18: 10 | J18: =SUM(L18:W18) -> 100 | K18: 10 | R18: 50 | S18: 50 | X18: =SUM(Y18:AJ18) -> 110 | Y18: =ROUND(L18*(100+$K18)/100,0) -> 0 | Z18: 0 | AA18: =ROUND(N18*(100+$K18)/100,0) -> 0 | AB18: =ROUND(O18*(100+$K18)/100,0) -> 0 | AC18: =ROUND(P18*(100+$K18)/100,0) -> 0 | AD18: =ROUND(Q18*(100+$K18)/100,0) -> 0 | AE18: =ROUND(R18*(100+$K18)/100,0) -> 55 | AF18: =ROUND(S18*(100+$K18)/100,0) -> 55 | AG18: =ROUND(T18*(100+$K18)/100,0) -> 0 | AH18: =ROUND(U18*(100+$K18)/100,0) -> 0 | ... AJ18: =ROUND(W18*(100+$K18)/100,0) -> 0
A19: SOUTH | B19: Surrey LP | C19: Surrey LP | D19: UKPN_SE | E19: Surrey Lamppost WP5 | F19: =J19*Assumption!$B$2 -> 100000 | G19: =J19*Assumption!$B$3 -> 100000 | H19: =J19*Assumption!$B$4 -> 100000 | I19: 10 | J19: =SUM(L19:W19) -> 100 | K19: 10 | S19: 50 | T19: 50 | X19: =SUM(Y19:AJ19) -> 110 | Y19: =ROUND(L19*(100+$K19)/100,0) -> 0 | Z19: 0 | AA19: =ROUND(N19*(100+$K19)/100,0) -> 0 | AB19: =ROUND(O19*(100+$K19)/100,0) -> 0 | AC19: =ROUND(P19*(100+$K19)/100,0) -> 0 | AD19: =ROUND(Q19*(100+$K19)/100,0) -> 0 | AE19: =ROUND(R19*(100+$K19)/100,0) -> 0 | AF19: =ROUND(S19*(100+$K19)/100,0) -> 55 | AG19: =ROUND(T19*(100+$K19)/100,0) -> 55 | AH19: =ROUND(U19*(100+$K19)/100,0) -> 0 | ... AJ19: =ROUND(W19*(100+$K19)/100,0) -> 0
A20: SOUTH | B20: Surrey LP | C20: Surrey LP | D20: UKPN_SE | E20: Surrey Lamppost WP6 | F20: =J20*Assumption!$B$2 -> 100000 | G20: =J20*Assumption!$B$3 -> 100000 | H20: =J20*Assumption!$B$4 -> 100000 | I20: 10 | J20: =SUM(L20:W20) -> 100 | K20: 10 | T20: 50 | U20: 50 | X20: =SUM(Y20:AJ20) -> 110 | Y20: =ROUND(L20*(100+$K20)/100,0) -> 0 | Z20: 0 | AA20: =ROUND(N20*(100+$K20)/100,0) -> 0 | AB20: =ROUND(O20*(100+$K20)/100,0) -> 0 | AC20: =ROUND(P20*(100+$K20)/100,0) -> 0 | AD20: =ROUND(Q20*(100+$K20)/100,0) -> 0 | AE20: =ROUND(R20*(100+$K20)/100,0) -> 0 | AF20: =ROUND(S20*(100+$K20)/100,0) -> 0 | AG20: =ROUND(T20*(100+$K20)/100,0) -> 55 | AH20: =ROUND(U20*(100+$K20)/100,0) -> 55 | ... AJ20: =ROUND(W20*(100+$K20)/100,0) -> 0
A21: SOUTH | B21: Surrey LP | C21: Surrey LP | D21: UKPN_SE | E21: Surrey Lamppost WP7 | F21: =J21*Assumption!$B$2 -> 100000 | G21: =J21*Assumption!$B$3 -> 100000 | H21: =J21*Assumption!$B$4 -> 100000 | I21: 10 | J21: =SUM(L21:W21) -> 100 | K21: 10 | U21: 50 | V21: 50 | X21: =SUM(Y21:AJ21) -> 110 | Y21: =ROUND(L21*(100+$K21)/100,0) -> 0 | Z21: 0 | AA21: =ROUND(N21*(100+$K21)/100,0) -> 0 | AB21: =ROUND(O21*(100+$K21)/100,0) -> 0 | AC21: =ROUND(P21*(100+$K21)/100,0) -> 0 | AD21: =ROUND(Q21*(100+$K21)/100,0) -> 0 | AE21: =ROUND(R21*(100+$K21)/100,0) -> 0 | AF21: =ROUND(S21*(100+$K21)/100,0) -> 0 | AG21: =ROUND(T21*(100+$K21)/100,0) -> 0 | AH21: =ROUND(U21*(100+$K21)/100,0) -> 55 | ... AJ21: =ROUND(W21*(100+$K21)/100,0) -> 0
A22: SOUTH | B22: Surrey LP | C22: Surrey LP | D22: UKPN_SE | E22: Surrey Lamppost WP8 | F22: =J22*Assumption!$B$2 -> 100000 | G22: =J22*Assumption!$B$3 -> 100000 | H22: =J22*Assumption!$B$4 -> 100000 | I22: 10 | J22: =SUM(L22:W22) -> 100 | K22: 10 | V22: 50 | W22: 50 | X22: =SUM(Y22:AJ22) -> 110 | Y22: =ROUND(L22*(100+$K22)/100,0) -> 0 | Z22: 0 | AA22: =ROUND(N22*(100+$K22)/100,0) -> 0 | AB22: =ROUND(O22*(100+$K22)/100,0) -> 0 | AC22: =ROUND(P22*(100+$K22)/100,0) -> 0 | AD22: =ROUND(Q22*(100+$K22)/100,0) -> 0 | AE22: =ROUND(R22*(100+$K22)/100,0) -> 0 | AF22: =ROUND(S22*(100+$K22)/100,0) -> 0 | AG22: =ROUND(T22*(100+$K22)/100,0) -> 0 | AH22: =ROUND(U22*(100+$K22)/100,0) -> 0 | ... AJ22: =ROUND(W22*(100+$K22)/100,0) -> 55
A23: SOUTH | B23: Surrey LP | C23: Surrey LP | D23: UKPN_SE | E23: Surrey Lamppost WP9 | F23: =J23*Assumption!$B$2 -> 50000 | G23: =J23*Assumption!$B$3 -> 50000 | H23: =J23*Assumption!$B$4 -> 50000 | I23: 10 | J23: =SUM(L23:W23) -> 50 | K23: 10 | W23: 50 | X23: =SUM(Y23:AJ23) -> 55 | Y23: =ROUND(L23*(100+$K23)/100,0) -> 0 | Z23: 0 | AA23: =ROUND(N23*(100+$K23)/100,0) -> 0 | AB23: =ROUND(O23*(100+$K23)/100,0) -> 0 | AC23: =ROUND(P23*(100+$K23)/100,0) -> 0 | AD23: =ROUND(Q23*(100+$K23)/100,0) -> 0 | AE23: =ROUND(R23*(100+$K23)/100,0) -> 0 | AF23: =ROUND(S23*(100+$K23)/100,0) -> 0 | AG23: =ROUND(T23*(100+$K23)/100,0) -> 0 | AH23: =ROUND(U23*(100+$K23)/100,0) -> 0 | ... AJ23: =ROUND(W23*(100+$K23)/100,0) -> 55
A24: SOUTH | B24: Surrey LP | C24: Surrey LP | D24: UKPN_SE | E24: Surrey Lamppost WP10 | F24: 0 | G24: =J24*Assumption!$B$3 -> 0 | H24: =J24*Assumption!$B$4 -> 0 | I24: 10 | J24: =SUM(L24:W24) -> 0 | K24: 10 | X24: =SUM(Y24:AJ24) -> 0 | Y24: =ROUND(L24*(100+$K24)/100,0) -> 0 | Z24: 0 | AA24: =ROUND(N24*(100+$K24)/100,0) -> 0 | AB24: =ROUND(O24*(100+$K24)/100,0) -> 0 | AC24: =ROUND(P24*(100+$K24)/100,0) -> 0 | AD24: =ROUND(Q24*(100+$K24)/100,0) -> 0 | AE24: =ROUND(R24*(100+$K24)/100,0) -> 0 | AF24: =ROUND(S24*(100+$K24)/100,0) -> 0 | AG24: =ROUND(T24*(100+$K24)/100,0) -> 0 | AH24: =ROUND(U24*(100+$K24)/100,0) -> 0 | ... AJ24: =ROUND(W24*(100+$K24)/100,0) -> 0
A25: SOUTH | B25: Surrey LP | C25: Surrey LP | D25: UKPN_SE | E25: Surrey Lamppost WP11 | F25: 0 | G25: =J25*Assumption!$B$3 -> 0 | H25: =J25*Assumption!$B$4 -> 0 | I25: 10 | J25: =SUM(L25:W25) -> 0 | K25: 10 | X25: =SUM(Y25:AJ25) -> 0 | Y25: =ROUND(L25*(100+$K25)/100,0) -> 0 | Z25: 0 | AA25: =ROUND(N25*(100+$K25)/100,0) -> 0 | AB25: =ROUND(O25*(100+$K25)/100,0) -> 0 | AC25: =ROUND(P25*(100+$K25)/100,0) -> 0 | AD25: =ROUND(Q25*(100+$K25)/100,0) -> 0 | AE25: =ROUND(R25*(100+$K25)/100,0) -> 0 | AF25: =ROUND(S25*(100+$K25)/100,0) -> 0 | AG25: =ROUND(T25*(100+$K25)/100,0) -> 0 | AH25: =ROUND(U25*(100+$K25)/100,0) -> 0 | ... AJ25: =ROUND(W25*(100+$K25)/100,0) -> 0
A26: SOUTH | B26: Plymouth | C26: Plymouth | D26: WPD_S | E26: Plymouth WP1 | F26: 111000 | G26: =J26*Assumption!$B$3 -> 50000 | H26: =J26*Assumption!$B$4 -> 50000 | I26: 10 | J26: =SUM(L26:W26) -> 50 | K26: 10 | L26: 0 | M26: 0 | N26: 0 | O26: 50 | P26: 0 | Q26: 0 | R26: 0 | S26: 0 | T26: 0 | U26: 0 | V26: 0 | W26: 0 | X26: =SUM(Y26:AJ26) -> 55 | Y26: =ROUND(L26*(100+$K26)/100,0) -> 0 | Z26: 0 | AA26: =ROUND(N26*(100+$K26)/100,0) -> 0 | AB26: =ROUND(O26*(100+$K26)/100,0) -> 55 | AC26: =ROUND(P26*(100+$K26)/100,0) -> 0 | AD26: =ROUND(Q26*(100+$K26)/100,0) -> 0 | AE26: =ROUND(R26*(100+$K26)/100,0) -> 0 | AF26: =ROUND(S26*(100+$K26)/100,0) -> 0 | AG26: =ROUND(T26*(100+$K26)/100,0) -> 0 | AH26: =ROUND(U26*(100+$K26)/100,0) -> 0 | ... AJ26: =ROUND(W26*(100+$K26)/100,0) -> 0
A27: SOUTH | B27: Plymouth | C27: Plymouth | D27: WPD_S | E27: Plymouth WP2 | F27: 111000 | G27: =J27*Assumption!$B$3 -> 100000 | H27: =J27*Assumption!$B$4 -> 100000 | I27: 10 | J27: =SUM(L27:W27) -> 100 | K27: 10 | L27: 0 | M27: 0 | N27: 0 | O27: 0 | P27: 50 | Q27: 50 | R27: 0 | S27: 0 | T27: 0 | U27: 0 | V27: 0 | W27: 0 | X27: =SUM(Y27:AJ27) -> 110 | Y27: =ROUND(L27*(100+$K27)/100,0) -> 0 | Z27: 0 | AA27: =ROUND(N27*(100+$K27)/100,0) -> 0 | AB27: =ROUND(O27*(100+$K27)/100,0) -> 0 | AC27: =ROUND(P27*(100+$K27)/100,0) -> 55 | AD27: =ROUND(Q27*(100+$K27)/100,0) -> 55 | AE27: =ROUND(R27*(100+$K27)/100,0) -> 0 | AF27: =ROUND(S27*(100+$K27)/100,0) -> 0 | AG27: =ROUND(T27*(100+$K27)/100,0) -> 0 | AH27: =ROUND(U27*(100+$K27)/100,0) -> 0 | ... AJ27: =ROUND(W27*(100+$K27)/100,0) -> 0
A28: SOUTH | B28: Plymouth | C28: Plymouth | D28: WPD_S | E28: Plymouth WP3 | F28: 150000 | G28: =J28*Assumption!$B$3 -> 150000 | H28: =J28*Assumption!$B$4 -> 150000 | I28: 10 | J28: =SUM(L28:W28) -> 150 | K28: 10 | L28: 0 | M28: 0 | N28: 0 | O28: 0 | P28: 0 | Q28: 0 | R28: 50 | S28: 50 | T28: 50 | U28: 0 | V28: 0 | W28: 0 | X28: =SUM(Y28:AJ28) -> 165 | Y28: =ROUND(L28*(100+$K28)/100,0) -> 0 | Z28: 0 | AA28: =ROUND(N28*(100+$K28)/100,0) -> 0 | AB28: =ROUND(O28*(100+$K28)/100,0) -> 0 | AC28: =ROUND(P28*(100+$K28)/100,0) -> 0 | AD28: =ROUND(Q28*(100+$K28)/100,0) -> 0 | AE28: =ROUND(R28*(100+$K28)/100,0) -> 55 | AF28: =ROUND(S28*(100+$K28)/100,0) -> 55 | AG28: =ROUND(T28*(100+$K28)/100,0) -> 55 | AH28: =ROUND(U28*(100+$K28)/100,0) -> 0 | ... AJ28: =ROUND(W28*(100+$K28)/100,0) -> 0
A29: SOUTH | B29: Plymouth | C29: Plymouth | D29: WPD_S | E29: Plymouth WP4 | F29: 150000 | G29: =J29*Assumption!$B$3 -> 150000 | H29: =J29*Assumption!$B$4 -> 150000 | I29: 10 | J29: =SUM(L29:W29) -> 150 | K29: 10 | L29: 0 | M29: 0 | N29: 0 | O29: 0 | P29: 0 | Q29: 0 | R29: 0 | S29: 0 | T29: 50 | U29: 50 | V29: 50 | W29: 0 | X29: =SUM(Y29:AJ29) -> 165 | Y29: =ROUND(L29*(100+$K29)/100,0) -> 0 | Z29: 0 | AA29: =ROUND(N29*(100+$K29)/100,0) -> 0 | AB29: =ROUND(O29*(100+$K29)/100,0) -> 0 | AC29: =ROUND(P29*(100+$K29)/100,0) -> 0 | AD29: =ROUND(Q29*(100+$K29)/100,0) -> 0 | AE29: =ROUND(R29*(100+$K29)/100,0) -> 0 | AF29: =ROUND(S29*(100+$K29)/100,0) -> 0 | AG29: =ROUND(T29*(100+$K29)/100,0) -> 55 | AH29: =ROUND(U29*(100+$K29)/100,0) -> 55 | ... AJ29: =ROUND(W29*(100+$K29)/100,0) -> 0
A30: SOUTH | B30: Plymouth | C30: Plymouth | D30: WPD_S | E30: Plymouth WP5 | F30: 30000 | G30: =J30*Assumption!$B$3 -> 50000 | H30: =J30*Assumption!$B$4 -> 50000 | I30: 10 | J30: =SUM(L30:W30) -> 50 | K30: 10 | L30: 0 | M30: 0 | N30: 0 | O30: 0 | P30: 0 | Q30: 0 | R30: 0 | S30: 0 | T30: 0 | U30: 0 | V30: 0 | W30: 50 | X30: =SUM(Y30:AJ30) -> 55 | Y30: =ROUND(L30*(100+$K30)/100,0) -> 0 | Z30: 0 | AA30: =ROUND(N30*(100+$K30)/100,0) -> 0 | AB30: =ROUND(O30*(100+$K30)/100,0) -> 0 | AC30: =ROUND(P30*(100+$K30)/100,0) -> 0 | AD30: =ROUND(Q30*(100+$K30)/100,0) -> 0 | AE30: =ROUND(R30*(100+$K30)/100,0) -> 0 | AF30: =ROUND(S30*(100+$K30)/100,0) -> 0 | AG30: =ROUND(T30*(100+$K30)/100,0) -> 0 | AH30: =ROUND(U30*(100+$K30)/100,0) -> 0 | ... AJ30: =ROUND(W30*(100+$K30)/100,0) -> 55
A31: SOUTH | B31: Bournemouth, Christchurch & Poole | C31: Bournemouth, Christchurch & Poole | D31: WPD_S | E31: Bournemouth, Christchurch and Poole WP1 | F31: 195000 | G31: =J31*Assumption!$B$3 -> 200000 | H31: =J31*Assumption!$B$4 -> 200000 | I31: 10 | J31: =SUM(L31:W31) -> 200 | K31: 10 | T31: 50 | U31: 50 | V31: 50 | W31: 50 | X31: =SUM(Y31:AJ31) -> 220 | Y31: =ROUND(L31*(100+$K31)/100,0) -> 0 | Z31: 0 | AA31: =ROUND(N31*(100+$K31)/100,0) -> 0 | AB31: =ROUND(O31*(100+$K31)/100,0) -> 0 | AC31: =ROUND(P31*(100+$K31)/100,0) -> 0 | AD31: =ROUND(Q31*(100+$K31)/100,0) -> 0 | AE31: =ROUND(R31*(100+$K31)/100,0) -> 0 | AF31: =ROUND(S31*(100+$K31)/100,0) -> 0 | AG31: =ROUND(T31*(100+$K31)/100,0) -> 55 | AH31: =ROUND(U31*(100+$K31)/100,0) -> 55 | ... AJ31: =ROUND(W31*(100+$K31)/100,0) -> 55
A32: SOUTH | B32: Bournemouth, Christchurch & Poole | C32: Bournemouth, Christchurch & Poole | D32: WPD_S | E32: Bournemouth, Christchurch and Poole WP2 | F32: 0 | G32: =J32*Assumption!$B$3 -> 0 | H32: =J32*Assumption!$B$4 -> 0 | I32: 10 | J32: =SUM(L32:W32) -> 0 | K32: 10 | X32: =SUM(Y32:AJ32) -> 0 | Y32: =ROUND(L32*(100+$K32)/100,0) -> 0 | Z32: 0 | AA32: =ROUND(N32*(100+$K32)/100,0) -> 0 | AB32: =ROUND(O32*(100+$K32)/100,0) -> 0 | AC32: =ROUND(P32*(100+$K32)/100,0) -> 0 | AD32: =ROUND(Q32*(100+$K32)/100,0) -> 0 | AE32: =ROUND(R32*(100+$K32)/100,0) -> 0 | AF32: =ROUND(S32*(100+$K32)/100,0) -> 0 | AG32: =ROUND(T32*(100+$K32)/100,0) -> 0 | AH32: =ROUND(U32*(100+$K32)/100,0) -> 0 | ... AJ32: =ROUND(W32*(100+$K32)/100,0) -> 0
A33: SOUTH | B33: Bournemouth, Christchurch & Poole | C33: Bournemouth, Christchurch & Poole | D33: WPD_S | E33: Bournemouth, Christchurch and Poole WP3 | F33: 0 | G33: =J33*Assumption!$B$3 -> 0 | H33: =J33*Assumption!$B$4 -> 0 | I33: 10 | J33: =SUM(L33:W33) -> 0 | K33: 10 | X33: =SUM(Y33:AJ33) -> 0 | Y33: =ROUND(L33*(100+$K33)/100,0) -> 0 | Z33: 0 | AA33: =ROUND(N33*(100+$K33)/100,0) -> 0 | AB33: =ROUND(O33*(100+$K33)/100,0) -> 0 | AC33: =ROUND(P33*(100+$K33)/100,0) -> 0 | AD33: =ROUND(Q33*(100+$K33)/100,0) -> 0 | AE33: =ROUND(R33*(100+$K33)/100,0) -> 0 | AF33: =ROUND(S33*(100+$K33)/100,0) -> 0 | AG33: =ROUND(T33*(100+$K33)/100,0) -> 0 | AH33: =ROUND(U33*(100+$K33)/100,0) -> 0 | ... AJ33: =ROUND(W33*(100+$K33)/100,0) -> 0
A34: SOUTH | B34: Dorset | C34: Dorset | D34: WPD_S | E34: Dorset WP1 | F34: 195000 | G34: =J34*Assumption!$B$3 -> 200000 | H34: =J34*Assumption!$B$4 -> 200000 | I34: 10 | J34: =SUM(L34:W34) -> 200 | K34: 10 | S34: 50 | T34: 50 | U34: 50 | V34: 50 | X34: =SUM(Y34:AJ34) -> 220 | Y34: =ROUND(L34*(100+$K34)/100,0) -> 0 | Z34: 0 | AA34: =ROUND(N34*(100+$K34)/100,0) -> 0 | AB34: =ROUND(O34*(100+$K34)/100,0) -> 0 | AC34: =ROUND(P34*(100+$K34)/100,0) -> 0 | AD34: =ROUND(Q34*(100+$K34)/100,0) -> 0 | AE34: =ROUND(R34*(100+$K34)/100,0) -> 0 | AF34: =ROUND(S34*(100+$K34)/100,0) -> 55 | AG34: =ROUND(T34*(100+$K34)/100,0) -> 55 | AH34: =ROUND(U34*(100+$K34)/100,0) -> 55 | ... AJ34: =ROUND(W34*(100+$K34)/100,0) -> 0
A35: SOUTH | B35: Dorset | C35: Dorset | D35: WPD_S | E35: Dorset WP2 | F35: 60000 | G35: =J35*Assumption!$B$3 -> 50000 | H35: =J35*Assumption!$B$4 -> 50000 | I35: 10 | J35: =SUM(L35:W35) -> 50 | K35: 10 | W35: 50 | X35: =SUM(Y35:AJ35) -> 55 | Y35: =ROUND(L35*(100+$K35)/100,0) -> 0 | Z35: 0 | AA35: =ROUND(N35*(100+$K35)/100,0) -> 0 | AB35: =ROUND(O35*(100+$K35)/100,0) -> 0 | AC35: =ROUND(P35*(100+$K35)/100,0) -> 0 | AD35: =ROUND(Q35*(100+$K35)/100,0) -> 0 | AE35: =ROUND(R35*(100+$K35)/100,0) -> 0 | AF35: =ROUND(S35*(100+$K35)/100,0) -> 0 | AG35: =ROUND(T35*(100+$K35)/100,0) -> 0 | AH35: =ROUND(U35*(100+$K35)/100,0) -> 0 | ... AJ35: =ROUND(W35*(100+$K35)/100,0) -> 55
A36: SOUTH | B36: Dorset | C36: Dorset | D36: WPD_S | E36: Dorset WP3 | F36: 0 | G36: =J36*Assumption!$B$3 -> 0 | H36: =J36*Assumption!$B$4 -> 0 | I36: 10 | J36: =SUM(L36:W36) -> 0 | K36: 10 | X36: =SUM(Y36:AJ36) -> 0 | Y36: =ROUND(L36*(100+$K36)/100,0) -> 0 | Z36: 0 | AA36: =ROUND(N36*(100+$K36)/100,0) -> 0 | AB36: =ROUND(O36*(100+$K36)/100,0) -> 0 | AC36: =ROUND(P36*(100+$K36)/100,0) -> 0 | AD36: =ROUND(Q36*(100+$K36)/100,0) -> 0 | AE36: =ROUND(R36*(100+$K36)/100,0) -> 0 | AF36: =ROUND(S36*(100+$K36)/100,0) -> 0 | AG36: =ROUND(T36*(100+$K36)/100,0) -> 0 | AH36: =ROUND(U36*(100+$K36)/100,0) -> 0 | ... AJ36: =ROUND(W36*(100+$K36)/100,0) -> 0
A37: SOUTH | B37: West Sussex | C37: West Sussex | D37: UKPN_SE | E37: West Sussex - Phase 4 WP2 | F37: 132000 | G37: =J37*Assumption!$B$3 -> 250000 | H37: =J37*Assumption!$B$4 -> 250000 | I37: 10 | J37: =SUM(L37:W37) -> 250 | K37: 10 | L37: 50 | N37: 50 | R37: 50 | S37: 50 | T37: 50 | X37: =SUM(Y37:AJ37) -> 275 | Y37: =ROUND(L37*(100+$K37)/100,0) -> 55 | Z37: 0 | AA37: =ROUND(N37*(100+$K37)/100,0) -> 55 | AB37: =ROUND(O37*(100+$K37)/100,0) -> 0 | AC37: =ROUND(P37*(100+$K37)/100,0) -> 0 | AD37: =ROUND(Q37*(100+$K37)/100,0) -> 0 | AE37: =ROUND(R37*(100+$K37)/100,0) -> 55 | AF37: =ROUND(S37*(100+$K37)/100,0) -> 55 | AG37: =ROUND(T37*(100+$K37)/100,0) -> 55 | AH37: =ROUND(U37*(100+$K37)/100,0) -> 0 | ... AJ37: =ROUND(W37*(100+$K37)/100,0) -> 0
A38: SOUTH | B38: Wealden | C38: Wealden | D38: UKPN_SE | E38: Wealden | F38: 18000 | G38: =J38*Assumption!$B$3 -> 100000 | H38: =J38*Assumption!$B$4 -> 100000 | I38: 10 | J38: =SUM(L38:W38) -> 100 | K38: 10 | L38: 50 | N38: 50 | X38: =SUM(Y38:AJ38) -> 110 | Y38: =ROUND(L38*(100+$K38)/100,0) -> 55 | Z38: 0 | AA38: =ROUND(N38*(100+$K38)/100,0) -> 55 | AB38: =ROUND(O38*(100+$K38)/100,0) -> 0 | AC38: =ROUND(P38*(100+$K38)/100,0) -> 0 | AD38: =ROUND(Q38*(100+$K38)/100,0) -> 0 | AE38: =ROUND(R38*(100+$K38)/100,0) -> 0 | AF38: =ROUND(S38*(100+$K38)/100,0) -> 0 | AG38: =ROUND(T38*(100+$K38)/100,0) -> 0 | AH38: =ROUND(U38*(100+$K38)/100,0) -> 0 | ... AJ38: =ROUND(W38*(100+$K38)/100,0) -> 0
A39: SOUTH | B39: Havering | C39: Havering | D39: UKPN_LPN | E39: Havering | F39: 33000 | G39: =J39*Assumption!$B$3 -> 100000 | H39: =J39*Assumption!$B$4 -> 100000 | I39: 10 | J39: =SUM(L39:W39) -> 100 | K39: 10 | M39: 50 | O39: 50 | X39: =SUM(Y39:AJ39) -> 68 | Y39: =ROUND(L39*(100+$K39)/100,0) -> 0 | Z39: 13 | AA39: =ROUND(N39*(100+$K39)/100,0) -> 0 | AB39: =ROUND(O39*(100+$K39)/100,0) -> 55 | AC39: =ROUND(P39*(100+$K39)/100,0) -> 0 | AD39: =ROUND(Q39*(100+$K39)/100,0) -> 0 | AE39: =ROUND(R39*(100+$K39)/100,0) -> 0 | AF39: =ROUND(S39*(100+$K39)/100,0) -> 0 | AG39: =ROUND(T39*(100+$K39)/100,0) -> 0 | AH39: =ROUND(U39*(100+$K39)/100,0) -> 0 | ... AJ39: =ROUND(W39*(100+$K39)/100,0) -> 0
A40: SOUTH | B40: Dorset - LEVI Pilot WP1 | C40: Dorset - LEVI Pilot WP1 | D40: WPD_S | E40: Dorset - LEVI Pilot WP1 | F40: 90000 | G40: =J40*Assumption!$B$3 -> 50000 | H40: =J40*Assumption!$B$4 -> 50000 | I40: 10 | J40: =SUM(L40:W40) -> 50 | K40: 10 | R40: 50 | X40: =SUM(Y40:AJ40) -> 55 | Y40: =ROUND(L40*(100+$K40)/100,0) -> 0 | Z40: 0 | AA40: =ROUND(N40*(100+$K40)/100,0) -> 0 | AB40: =ROUND(O40*(100+$K40)/100,0) -> 0 | AC40: =ROUND(P40*(100+$K40)/100,0) -> 0 | AD40: =ROUND(Q40*(100+$K40)/100,0) -> 0 | AE40: =ROUND(R40*(100+$K40)/100,0) -> 55 | AF40: =ROUND(S40*(100+$K40)/100,0) -> 0 | AG40: =ROUND(T40*(100+$K40)/100,0) -> 0 | AH40: =ROUND(U40*(100+$K40)/100,0) -> 0 | ... AJ40: =ROUND(W40*(100+$K40)/100,0) -> 0
A41: SOUTH | B41: Dorset - LEVI Pilot WP2 | C41: Dorset - LEVI Pilot WP2 | D41: WPD_S | E41: Dorset - LEVI Pilot WP2 | F41: 0 | G41: =J41*Assumption!$B$3 -> 0 | H41: =J41*Assumption!$B$4 -> 0 | I41: 10 | J41: =SUM(L41:W41) -> 0 | K41: 10 | X41: =SUM(Y41:AJ41) -> 0 | Y41: =ROUND(L41*(100+$K41)/100,0) -> 0 | Z41: 0 | AA41: =ROUND(N41*(100+$K41)/100,0) -> 0 | AB41: =ROUND(O41*(100+$K41)/100,0) -> 0 | AC41: =ROUND(P41*(100+$K41)/100,0) -> 0 | AD41: =ROUND(Q41*(100+$K41)/100,0) -> 0 | AE41: =ROUND(R41*(100+$K41)/100,0) -> 0 | AF41: =ROUND(S41*(100+$K41)/100,0) -> 0 | AG41: =ROUND(T41*(100+$K41)/100,0) -> 0 | AH41: =ROUND(U41*(100+$K41)/100,0) -> 0 | ... AJ41: =ROUND(W41*(100+$K41)/100,0) -> 0
A42: Central & Wales | B42: Windsor & Maidenhead | C42: Windsor & Maidenhead | D42: WPD_SM | E42: Windsor & Maidenhead WPX | F42: 0 | G42: =J42*Assumption!$B$3 -> 0 | H42: =J42*Assumption!$B$4 -> 0 | I42: 10 | J42: =SUM(L42:W42) -> 0 | K42: 10 | X42: =SUM(Y42:AJ42) -> 0 | Y42: =ROUND(L42*(100+$K42)/100,0) -> 0 | Z42: 0 | AA42: =ROUND(N42*(100+$K42)/100,0) -> 0 | AB42: =ROUND(O42*(100+$K42)/100,0) -> 0 | AC42: =ROUND(P42*(100+$K42)/100,0) -> 0 | AD42: =ROUND(Q42*(100+$K42)/100,0) -> 0 | AE42: =ROUND(R42*(100+$K42)/100,0) -> 0 | AF42: =ROUND(S42*(100+$K42)/100,0) -> 0 | AG42: =ROUND(T42*(100+$K42)/100,0) -> 0 | AH42: =ROUND(U42*(100+$K42)/100,0) -> 0 | ... AJ42: =ROUND(W42*(100+$K42)/100,0) -> 0
A43: Central & Wales | B43: West Berkshire | C43: West Berkshire | D43: WPD_SM | E43: West Berkshire WP1 | F43: 150000 | G43: =J43*Assumption!$B$3 -> 200000 | H43: =J43*Assumption!$B$4 -> 200000 | I43: 10 | J43: =SUM(L43:W43) -> 200 | K43: 10 | P43: 50 | Q43: 50 | R43: 50 | S43: 50 | X43: =SUM(Y43:AJ43) -> 220 | Y43: =ROUND(L43*(100+$K43)/100,0) -> 0 | Z43: 0 | AA43: =ROUND(N43*(100+$K43)/100,0) -> 0 | AB43: =ROUND(O43*(100+$K43)/100,0) -> 0 | AC43: =ROUND(P43*(100+$K43)/100,0) -> 55 | AD43: =ROUND(Q43*(100+$K43)/100,0) -> 55 | AE43: =ROUND(R43*(100+$K43)/100,0) -> 55 | AF43: =ROUND(S43*(100+$K43)/100,0) -> 55 | AG43: =ROUND(T43*(100+$K43)/100,0) -> 0 | AH43: =ROUND(U43*(100+$K43)/100,0) -> 0 | ... AJ43: =ROUND(W43*(100+$K43)/100,0) -> 0
A44: Central & Wales | B44: West Berkshire | C44: West Berkshire | D44: WPD_SM | E44: West Berkshire WP2 | F44: 157500 | G44: =J44*Assumption!$B$3 -> 200000 | H44: =J44*Assumption!$B$4 -> 200000 | I44: 10 | J44: =SUM(L44:W44) -> 200 | K44: 10 | S44: 50 | T44: 50 | U44: 50 | V44: 50 | X44: =SUM(Y44:AJ44) -> 220 | Y44: =ROUND(L44*(100+$K44)/100,0) -> 0 | Z44: 0 | AA44: =ROUND(N44*(100+$K44)/100,0) -> 0 | AB44: =ROUND(O44*(100+$K44)/100,0) -> 0 | AC44: =ROUND(P44*(100+$K44)/100,0) -> 0 | AD44: =ROUND(Q44*(100+$K44)/100,0) -> 0 | AE44: =ROUND(R44*(100+$K44)/100,0) -> 0 | AF44: =ROUND(S44*(100+$K44)/100,0) -> 55 | AG44: =ROUND(T44*(100+$K44)/100,0) -> 55 | AH44: =ROUND(U44*(100+$K44)/100,0) -> 55 | ... AJ44: =ROUND(W44*(100+$K44)/100,0) -> 0
A45: Central & Wales | B45: West Berkshire | C45: West Berkshire | D45: WPD_SM | E45: West Berkshire WP3 | F45: 30000 | G45: =J45*Assumption!$B$3 -> 50000 | H45: =J45*Assumption!$B$4 -> 50000 | I45: 10 | J45: =SUM(L45:W45) -> 50 | K45: 10 | W45: 50 | X45: =SUM(Y45:AJ45) -> 55 | Y45: =ROUND(L45*(100+$K45)/100,0) -> 0 | Z45: 0 | AA45: =ROUND(N45*(100+$K45)/100,0) -> 0 | AB45: =ROUND(O45*(100+$K45)/100,0) -> 0 | AC45: =ROUND(P45*(100+$K45)/100,0) -> 0 | AD45: =ROUND(Q45*(100+$K45)/100,0) -> 0 | AE45: =ROUND(R45*(100+$K45)/100,0) -> 0 | AF45: =ROUND(S45*(100+$K45)/100,0) -> 0 | AG45: =ROUND(T45*(100+$K45)/100,0) -> 0 | AH45: =ROUND(U45*(100+$K45)/100,0) -> 0 | ... AJ45: =ROUND(W45*(100+$K45)/100,0) -> 55
A46: Central & Wales | B46: North Northamptonshire | C46: North Northamptonshire | D46: WPD_SM | E46: North Northamptonshire WP1 | F46: 180000 | G46: =J46*Assumption!$B$3 -> 200000 | H46: =J46*Assumption!$B$4 -> 200000 | I46: 10 | J46: =SUM(L46:W46) -> 200 | K46: 10 | Q46: 50 | R46: 50 | S46: 50 | T46: 50 | X46: =SUM(Y46:AJ46) -> 220 | Y46: =ROUND(L46*(100+$K46)/100,0) -> 0 | Z46: 0 | AA46: =ROUND(N46*(100+$K46)/100,0) -> 0 | AB46: =ROUND(O46*(100+$K46)/100,0) -> 0 | AC46: =ROUND(P46*(100+$K46)/100,0) -> 0 | AD46: =ROUND(Q46*(100+$K46)/100,0) -> 55 | AE46: =ROUND(R46*(100+$K46)/100,0) -> 55 | AF46: =ROUND(S46*(100+$K46)/100,0) -> 55 | AG46: =ROUND(T46*(100+$K46)/100,0) -> 55 | AH46: =ROUND(U46*(100+$K46)/100,0) -> 0 | ... AJ46: =ROUND(W46*(100+$K46)/100,0) -> 0
A47: Central & Wales | B47: North Northamptonshire | C47: North Northamptonshire | D47: WPD_SM | E47: North Northamptonshire WP2 | F47: 165000 | G47: =J47*Assumption!$B$3 -> 200000 | H47: =J47*Assumption!$B$4 -> 200000 | I47: 10 | J47: =SUM(L47:W47) -> 200 | K47: 10 | T47: 50 | U47: 50 | V47: 50 | W47: 50 | X47: =SUM(Y47:AJ47) -> 220 | Y47: =ROUND(L47*(100+$K47)/100,0) -> 0 | Z47: 0 | AA47: =ROUND(N47*(100+$K47)/100,0) -> 0 | AB47: =ROUND(O47*(100+$K47)/100,0) -> 0 | AC47: =ROUND(P47*(100+$K47)/100,0) -> 0 | AD47: =ROUND(Q47*(100+$K47)/100,0) -> 0 | AE47: =ROUND(R47*(100+$K47)/100,0) -> 0 | AF47: =ROUND(S47*(100+$K47)/100,0) -> 0 | AG47: =ROUND(T47*(100+$K47)/100,0) -> 55 | AH47: =ROUND(U47*(100+$K47)/100,0) -> 55 | ... AJ47: =ROUND(W47*(100+$K47)/100,0) -> 55
A48: Central & Wales | B48: North Northamptonshire | C48: North Northamptonshire | D48: WPD_SM | E48: North Northamptonshire WP3 | F48: 0 | G48: =J48*Assumption!$B$3 -> 0 | H48: =J48*Assumption!$B$4 -> 0 | I48: 10 | J48: =SUM(L48:W48) -> 0 | K48: 10 | X48: =SUM(Y48:AJ48) -> 0 | Y48: =ROUND(L48*(100+$K48)/100,0) -> 0 | Z48: 0 | AA48: =ROUND(N48*(100+$K48)/100,0) -> 0 | AB48: =ROUND(O48*(100+$K48)/100,0) -> 0 | AC48: =ROUND(P48*(100+$K48)/100,0) -> 0 | AD48: =ROUND(Q48*(100+$K48)/100,0) -> 0 | AE48: =ROUND(R48*(100+$K48)/100,0) -> 0 | AF48: =ROUND(S48*(100+$K48)/100,0) -> 0 | AG48: =ROUND(T48*(100+$K48)/100,0) -> 0 | AH48: =ROUND(U48*(100+$K48)/100,0) -> 0 | ... AJ48: =ROUND(W48*(100+$K48)/100,0) -> 0
A49: Central & Wales | B49: Oxfordshire | C49: Oxfordshire | D49: WPD_SM | E49: Oxfordshire WP1 | F49: 165000 | G49: =J49*Assumption!$B$3 -> 200000 | H49: =J49*Assumption!$B$4 -> 200000 | I49: 10 | J49: =SUM(L49:W49) -> 200 | K49: 10 | P49: 50 | Q49: 50 | R49: 50 | S49: 50 | X49: =SUM(Y49:AJ49) -> 220 | Y49: =ROUND(L49*(100+$K49)/100,0) -> 0 | Z49: 0 | AA49: =ROUND(N49*(100+$K49)/100,0) -> 0 | AB49: =ROUND(O49*(100+$K49)/100,0) -> 0 | AC49: =ROUND(P49*(100+$K49)/100,0) -> 55 | AD49: =ROUND(Q49*(100+$K49)/100,0) -> 55 | AE49: =ROUND(R49*(100+$K49)/100,0) -> 55 | AF49: =ROUND(S49*(100+$K49)/100,0) -> 55 | AG49: =ROUND(T49*(100+$K49)/100,0) -> 0 | AH49: =ROUND(U49*(100+$K49)/100,0) -> 0 | ... AJ49: =ROUND(W49*(100+$K49)/100,0) -> 0
A50: Central & Wales | B50: Oxfordshire | C50: Oxfordshire | D50: WPD_SM | E50: Oxfordshire WP2 | F50: 162000 | G50: =J50*Assumption!$B$3 -> 200000 | H50: =J50*Assumption!$B$4 -> 200000 | I50: 10 | J50: =SUM(L50:W50) -> 200 | K50: 10 | S50: 50 | T50: 50 | U50: 50 | V50: 50 | X50: =SUM(Y50:AJ50) -> 220 | Y50: =ROUND(L50*(100+$K50)/100,0) -> 0 | Z50: 0 | AA50: =ROUND(N50*(100+$K50)/100,0) -> 0 | AB50: =ROUND(O50*(100+$K50)/100,0) -> 0 | AC50: =ROUND(P50*(100+$K50)/100,0) -> 0 | AD50: =ROUND(Q50*(100+$K50)/100,0) -> 0 | AE50: =ROUND(R50*(100+$K50)/100,0) -> 0 | AF50: =ROUND(S50*(100+$K50)/100,0) -> 55 | AG50: =ROUND(T50*(100+$K50)/100,0) -> 55 | AH50: =ROUND(U50*(100+$K50)/100,0) -> 55 | ... AJ50: =ROUND(W50*(100+$K50)/100,0) -> 0
A51: Central & Wales | B51: Oxfordshire | C51: Oxfordshire | D51: WPD_SM | E51: Oxfordshire WP3 | F51: 15000 | G51: =J51*Assumption!$B$3 -> 50000 | H51: =J51*Assumption!$B$4 -> 50000 | I51: 10 | J51: =SUM(L51:W51) -> 50 | K51: 10 | W51: 50 | X51: =SUM(Y51:AJ51) -> 55 | Y51: =ROUND(L51*(100+$K51)/100,0) -> 0 | Z51: 0 | AA51: =ROUND(N51*(100+$K51)/100,0) -> 0 | AB51: =ROUND(O51*(100+$K51)/100,0) -> 0 | AC51: =ROUND(P51*(100+$K51)/100,0) -> 0 | AD51: =ROUND(Q51*(100+$K51)/100,0) -> 0 | AE51: =ROUND(R51*(100+$K51)/100,0) -> 0 | AF51: =ROUND(S51*(100+$K51)/100,0) -> 0 | AG51: =ROUND(T51*(100+$K51)/100,0) -> 0 | AH51: =ROUND(U51*(100+$K51)/100,0) -> 0 | ... AJ51: =ROUND(W51*(100+$K51)/100,0) -> 55
A52: Central & Wales | B52: Oxfordshire | C52: Oxfordshire | D52: WPD_SM | E52: Oxfordshire WP4 | F52: 0 | G52: =J52*Assumption!$B$3 -> 0 | H52: =J52*Assumption!$B$4 -> 0 | I52: 10 | J52: =SUM(L52:W52) -> 0 | K52: 10 | X52: =SUM(Y52:AJ52) -> 0 | Y52: =ROUND(L52*(100+$K52)/100,0) -> 0 | Z52: 0 | AA52: =ROUND(N52*(100+$K52)/100,0) -> 0 | AB52: =ROUND(O52*(100+$K52)/100,0) -> 0 | AC52: =ROUND(P52*(100+$K52)/100,0) -> 0 | AD52: =ROUND(Q52*(100+$K52)/100,0) -> 0 | AE52: =ROUND(R52*(100+$K52)/100,0) -> 0 | AF52: =ROUND(S52*(100+$K52)/100,0) -> 0 | AG52: =ROUND(T52*(100+$K52)/100,0) -> 0 | AH52: =ROUND(U52*(100+$K52)/100,0) -> 0 | ... AJ52: =ROUND(W52*(100+$K52)/100,0) -> 0
A53: Central & Wales | B53: Oxfordshire | C53: Oxfordshire | D53: WPD_SM | E53: Oxfordshire WP5 | F53: 0 | G53: =J53*Assumption!$B$3 -> 0 | H53: =J53*Assumption!$B$4 -> 0 | I53: 10 | J53: =SUM(L53:W53) -> 0 | K53: 10 | X53: =SUM(Y53:AJ53) -> 0 | Y53: =ROUND(L53*(100+$K53)/100,0) -> 0 | Z53: 0 | AA53: =ROUND(N53*(100+$K53)/100,0) -> 0 | AB53: =ROUND(O53*(100+$K53)/100,0) -> 0 | AC53: =ROUND(P53*(100+$K53)/100,0) -> 0 | AD53: =ROUND(Q53*(100+$K53)/100,0) -> 0 | AE53: =ROUND(R53*(100+$K53)/100,0) -> 0 | AF53: =ROUND(S53*(100+$K53)/100,0) -> 0 | AG53: =ROUND(T53*(100+$K53)/100,0) -> 0 | AH53: =ROUND(U53*(100+$K53)/100,0) -> 0 | ... AJ53: =ROUND(W53*(100+$K53)/100,0) -> 0
A54: Central & Wales | B54: Bedford | C54: Bedford | D54: WPD_SM | E54: Bedford WP1 | F54: 135000 | G54: =J54*Assumption!$B$3 -> 150000 | H54: =J54*Assumption!$B$4 -> 150000 | I54: 10 | J54: =SUM(L54:W54) -> 150 | K54: 10 | T54: 50 | U54: 50 | V54: 50 | X54: =SUM(Y54:AJ54) -> 165 | Y54: =ROUND(L54*(100+$K54)/100,0) -> 0 | Z54: 0 | AA54: =ROUND(N54*(100+$K54)/100,0) -> 0 | AB54: =ROUND(O54*(100+$K54)/100,0) -> 0 | AC54: =ROUND(P54*(100+$K54)/100,0) -> 0 | AD54: =ROUND(Q54*(100+$K54)/100,0) -> 0 | AE54: =ROUND(R54*(100+$K54)/100,0) -> 0 | AF54: =ROUND(S54*(100+$K54)/100,0) -> 0 | AG54: =ROUND(T54*(100+$K54)/100,0) -> 55 | AH54: =ROUND(U54*(100+$K54)/100,0) -> 55 | ... AJ54: =ROUND(W54*(100+$K54)/100,0) -> 0
A55: Central & Wales | B55: Bedford | C55: Bedford | D55: WPD_SM | E55: Bedford WP2 | F55: 0 | G55: =J55*Assumption!$B$3 -> 0 | H55: =J55*Assumption!$B$4 -> 0 | I55: 10 | J55: =SUM(L55:W55) -> 0 | K55: 10 | X55: =SUM(Y55:AJ55) -> 0 | Y55: =ROUND(L55*(100+$K55)/100,0) -> 0 | Z55: 0 | AA55: =ROUND(N55*(100+$K55)/100,0) -> 0 | AB55: =ROUND(O55*(100+$K55)/100,0) -> 0 | AC55: =ROUND(P55*(100+$K55)/100,0) -> 0 | AD55: =ROUND(Q55*(100+$K55)/100,0) -> 0 | AE55: =ROUND(R55*(100+$K55)/100,0) -> 0 | AF55: =ROUND(S55*(100+$K55)/100,0) -> 0 | AG55: =ROUND(T55*(100+$K55)/100,0) -> 0 | AH55: =ROUND(U55*(100+$K55)/100,0) -> 0 | ... AJ55: =ROUND(W55*(100+$K55)/100,0) -> 0
A56: Central & Wales | B56: Bedford | C56: Bedford | D56: WPD_SM | E56: Bedford WP3 | F56: 0 | G56: =J56*Assumption!$B$3 -> 0 | H56: =J56*Assumption!$B$4 -> 0 | I56: 10 | J56: =SUM(L56:W56) -> 0 | K56: 10 | X56: =SUM(Y56:AJ56) -> 0 | Y56: =ROUND(L56*(100+$K56)/100,0) -> 0 | Z56: 0 | AA56: =ROUND(N56*(100+$K56)/100,0) -> 0 | AB56: =ROUND(O56*(100+$K56)/100,0) -> 0 | AC56: =ROUND(P56*(100+$K56)/100,0) -> 0 | AD56: =ROUND(Q56*(100+$K56)/100,0) -> 0 | AE56: =ROUND(R56*(100+$K56)/100,0) -> 0 | AF56: =ROUND(S56*(100+$K56)/100,0) -> 0 | AG56: =ROUND(T56*(100+$K56)/100,0) -> 0 | AH56: =ROUND(U56*(100+$K56)/100,0) -> 0 | ... AJ56: =ROUND(W56*(100+$K56)/100,0) -> 0
A57: Central & Wales | B57: Gloucester - F&F | C57: Gloucester - F&F | D57: WPD_SM | E57: Gloucester - F&F | F57: 27000 | G57: =J57*Assumption!$B$3 -> 50000 | H57: =J57*Assumption!$B$4 -> 50000 | I57: 10 | J57: =SUM(L57:W57) -> 50 | K57: 10 | N57: 50 | X57: =SUM(Y57:AJ57) -> 55 | Y57: =ROUND(L57*(100+$K57)/100,0) -> 0 | Z57: 0 | AA57: =ROUND(N57*(100+$K57)/100,0) -> 55 | AB57: =ROUND(O57*(100+$K57)/100,0) -> 0 | AC57: =ROUND(P57*(100+$K57)/100,0) -> 0 | AD57: =ROUND(Q57*(100+$K57)/100,0) -> 0 | AE57: =ROUND(R57*(100+$K57)/100,0) -> 0 | AF57: =ROUND(S57*(100+$K57)/100,0) -> 0 | AG57: =ROUND(T57*(100+$K57)/100,0) -> 0 | AH57: =ROUND(U57*(100+$K57)/100,0) -> 0 | ... AJ57: =ROUND(W57*(100+$K57)/100,0) -> 0
A58: Central & Wales | B58: Gloucester - GCC LEVI WP3 | C58: Gloucester - GCC LEVI WP3 | D58: WPD_SM | E58: Gloucester - GCC LEVI WP3 | F58: 36000 | G58: =J58*Assumption!$B$3 -> 100000 | H58: =J58*Assumption!$B$4 -> 100000 | I58: 10 | J58: =SUM(L58:W58) -> 100 | K58: 10 | M58: 50 | N58: 50 | X58: =SUM(Y58:AJ58) -> 77 | Y58: =ROUND(L58*(100+$K58)/100,0) -> 0 | Z58: 22 | AA58: =ROUND(N58*(100+$K58)/100,0) -> 55 | AB58: =ROUND(O58*(100+$K58)/100,0) -> 0 | AC58: =ROUND(P58*(100+$K58)/100,0) -> 0 | AD58: =ROUND(Q58*(100+$K58)/100,0) -> 0 | AE58: =ROUND(R58*(100+$K58)/100,0) -> 0 | AF58: =ROUND(S58*(100+$K58)/100,0) -> 0 | AG58: =ROUND(T58*(100+$K58)/100,0) -> 0 | AH58: =ROUND(U58*(100+$K58)/100,0) -> 0 | ... AJ58: =ROUND(W58*(100+$K58)/100,0) -> 0
A59: Central & Wales | B59: CCR | C59: CCR | D59: WPD_SM | E59: CCR | F59: 3000 | G59: =J59*Assumption!$B$3 -> 50000 | H59: =J59*Assumption!$B$4 -> 50000 | I59: 10 | J59: =SUM(L59:W59) -> 50 | K59: 10 | M59: 50 | X59: =SUM(Y59:AJ59) -> 2 | Y59: =ROUND(L59*(100+$K59)/100,0) -> 0 | Z59: 2 | AA59: =ROUND(N59*(100+$K59)/100,0) -> 0 | AB59: =ROUND(O59*(100+$K59)/100,0) -> 0 | AC59: =ROUND(P59*(100+$K59)/100,0) -> 0 | AD59: =ROUND(Q59*(100+$K59)/100,0) -> 0 | AE59: =ROUND(R59*(100+$K59)/100,0) -> 0 | AF59: =ROUND(S59*(100+$K59)/100,0) -> 0 | AG59: =ROUND(T59*(100+$K59)/100,0) -> 0 | AH59: =ROUND(U59*(100+$K59)/100,0) -> 0 | ... AJ59: =ROUND(W59*(100+$K59)/100,0) -> 0
A60: Central & Wales | B60: Barking & Dagenham | C60: Barking & Dagenham | D60: WPD_SM | E60: Barking & Dagenham | F60: 24000 | G60: =J60*Assumption!$B$3 -> 50000 | H60: =J60*Assumption!$B$4 -> 50000 | I60: 10 | J60: =SUM(L60:W60) -> 50 | K60: 10 | N60: 50 | X60: =SUM(Y60:AJ60) -> 55 | Y60: =ROUND(L60*(100+$K60)/100,0) -> 0 | Z60: 0 | AA60: =ROUND(N60*(100+$K60)/100,0) -> 55 | AB60: =ROUND(O60*(100+$K60)/100,0) -> 0 | AC60: =ROUND(P60*(100+$K60)/100,0) -> 0 | AD60: =ROUND(Q60*(100+$K60)/100,0) -> 0 | AE60: =ROUND(R60*(100+$K60)/100,0) -> 0 | AF60: =ROUND(S60*(100+$K60)/100,0) -> 0 | AG60: =ROUND(T60*(100+$K60)/100,0) -> 0 | AH60: =ROUND(U60*(100+$K60)/100,0) -> 0 | ... AJ60: =ROUND(W60*(100+$K60)/100,0) -> 0
A61: Central & Wales | B61: Suffolk | C61: Suffolk | D61: WPD_SM | E61: Suffolk | F61: 9000 | G61: =J61*Assumption!$B$3 -> 50000 | H61: =J61*Assumption!$B$4 -> 50000 | I61: 10 | J61: =SUM(L61:W61) -> 50 | K61: 10 | N61: 50 | X61: =SUM(Y61:AJ61) -> 55 | Y61: =ROUND(L61*(100+$K61)/100,0) -> 0 | Z61: 0 | AA61: =ROUND(N61*(100+$K61)/100,0) -> 55 | AB61: =ROUND(O61*(100+$K61)/100,0) -> 0 | AC61: =ROUND(P61*(100+$K61)/100,0) -> 0 | AD61: =ROUND(Q61*(100+$K61)/100,0) -> 0 | AE61: =ROUND(R61*(100+$K61)/100,0) -> 0 | AF61: =ROUND(S61*(100+$K61)/100,0) -> 0 | AG61: =ROUND(T61*(100+$K61)/100,0) -> 0 | AH61: =ROUND(U61*(100+$K61)/100,0) -> 0 | ... AJ61: =ROUND(W61*(100+$K61)/100,0) -> 0
A62: Central & Wales | B62: Ceredigion | C62: Ceredigion | D62: WPD_SM | E62: Ceredigion | F62: 102000 | G62: =J62*Assumption!$B$3 -> 100000 | H62: =J62*Assumption!$B$4 -> 100000 | I62: 10 | J62: =SUM(L62:W62) -> 100 | K62: 10 | N62: 50 | O62: 50 | X62: =SUM(Y62:AJ62) -> 110 | Y62: =ROUND(L62*(100+$K62)/100,0) -> 0 | Z62: 0 | AA62: =ROUND(N62*(100+$K62)/100,0) -> 55 | AB62: =ROUND(O62*(100+$K62)/100,0) -> 55 | AC62: =ROUND(P62*(100+$K62)/100,0) -> 0 | AD62: =ROUND(Q62*(100+$K62)/100,0) -> 0 | AE62: =ROUND(R62*(100+$K62)/100,0) -> 0 | AF62: =ROUND(S62*(100+$K62)/100,0) -> 0 | AG62: =ROUND(T62*(100+$K62)/100,0) -> 0 | AH62: =ROUND(U62*(100+$K62)/100,0) -> 0 | ... AJ62: =ROUND(W62*(100+$K62)/100,0) -> 0
A63: Midlands | B63: Midlands Connect - Leicestershire | C63: Midlands Connect - Leicestershire | D63: WPD_EM | E63: Midlands Connect - Leicestershire WP1 | F63: 127500 | G63: =J63*Assumption!$B$3 -> 200000 | H63: =J63*Assumption!$B$4 -> 200000 | I63: 10 | J63: =SUM(L63:W63) -> 200 | K63: 10 | T63: 50 | U63: 50 | V63: 50 | W63: 50 | X63: =SUM(Y63:AJ63) -> 220 | Y63: =ROUND(L63*(100+$K63)/100,0) -> 0 | Z63: 0 | AA63: =ROUND(N63*(100+$K63)/100,0) -> 0 | AB63: =ROUND(O63*(100+$K63)/100,0) -> 0 | AC63: =ROUND(P63*(100+$K63)/100,0) -> 0 | AD63: =ROUND(Q63*(100+$K63)/100,0) -> 0 | AE63: =ROUND(R63*(100+$K63)/100,0) -> 0 | AF63: =ROUND(S63*(100+$K63)/100,0) -> 0 | AG63: =ROUND(T63*(100+$K63)/100,0) -> 55 | AH63: =ROUND(U63*(100+$K63)/100,0) -> 55 | ... AJ63: =ROUND(W63*(100+$K63)/100,0) -> 55
A64: Midlands | B64: Midlands Connect - Leicestershire | C64: Midlands Connect - Leicestershire | D64: WPD_EM | E64: Midlands Connect - Leicestershire WP2 | F64: 52500 | G64: =J64*Assumption!$B$3 -> 100000 | H64: =J64*Assumption!$B$4 -> 100000 | I64: 10 | J64: =SUM(L64:W64) -> 100 | K64: 10 | V64: 50 | W64: 50 | X64: =SUM(Y64:AJ64) -> 110 | Y64: =ROUND(L64*(100+$K64)/100,0) -> 0 | Z64: 0 | AA64: =ROUND(N64*(100+$K64)/100,0) -> 0 | AB64: =ROUND(O64*(100+$K64)/100,0) -> 0 | AC64: =ROUND(P64*(100+$K64)/100,0) -> 0 | AD64: =ROUND(Q64*(100+$K64)/100,0) -> 0 | AE64: =ROUND(R64*(100+$K64)/100,0) -> 0 | AF64: =ROUND(S64*(100+$K64)/100,0) -> 0 | AG64: =ROUND(T64*(100+$K64)/100,0) -> 0 | AH64: =ROUND(U64*(100+$K64)/100,0) -> 0 | ... AJ64: =ROUND(W64*(100+$K64)/100,0) -> 55
A65: Midlands | B65: Midlands Connect - Leicestershire | C65: Midlands Connect - Leicestershire | D65: WPD_EM | E65: Midlands Connect - Leicestershire WP3 | F65: 0 | G65: =J65*Assumption!$B$3 -> 0 | H65: =J65*Assumption!$B$4 -> 0 | I65: 10 | J65: =SUM(L65:W65) -> 0 | K65: 10 | X65: =SUM(Y65:AJ65) -> 0 | Y65: =ROUND(L65*(100+$K65)/100,0) -> 0 | Z65: 0 | AA65: =ROUND(N65*(100+$K65)/100,0) -> 0 | AB65: =ROUND(O65*(100+$K65)/100,0) -> 0 | AC65: =ROUND(P65*(100+$K65)/100,0) -> 0 | AD65: =ROUND(Q65*(100+$K65)/100,0) -> 0 | AE65: =ROUND(R65*(100+$K65)/100,0) -> 0 | AF65: =ROUND(S65*(100+$K65)/100,0) -> 0 | AG65: =ROUND(T65*(100+$K65)/100,0) -> 0 | AH65: =ROUND(U65*(100+$K65)/100,0) -> 0 | ... AJ65: =ROUND(W65*(100+$K65)/100,0) -> 0
A66: Midlands | B66: Midlands Connect - Leicestershire | C66: Midlands Connect - Leicestershire | D66: WPD_EM | E66: Midlands Connect - Leicestershire WP4 | F66: 0 | G66: =J66*Assumption!$B$3 -> 0 | H66: =J66*Assumption!$B$4 -> 0 | I66: 10 | J66: =SUM(L66:W66) -> 0 | K66: 10 | X66: =SUM(Y66:AJ66) -> 0 | Y66: =ROUND(L66*(100+$K66)/100,0) -> 0 | Z66: 0 | AA66: =ROUND(N66*(100+$K66)/100,0) -> 0 | AB66: =ROUND(O66*(100+$K66)/100,0) -> 0 | AC66: =ROUND(P66*(100+$K66)/100,0) -> 0 | AD66: =ROUND(Q66*(100+$K66)/100,0) -> 0 | AE66: =ROUND(R66*(100+$K66)/100,0) -> 0 | AF66: =ROUND(S66*(100+$K66)/100,0) -> 0 | AG66: =ROUND(T66*(100+$K66)/100,0) -> 0 | AH66: =ROUND(U66*(100+$K66)/100,0) -> 0 | ... AJ66: =ROUND(W66*(100+$K66)/100,0) -> 0
A67: Midlands | B67: Midlands Connect - Rutland | C67: Midlands Connect - Rutland | D67: WPD_EM | E67: Midlands Connect - Rutland WP1 | F67: 127500 | G67: =J67*Assumption!$B$3 -> 200000 | H67: =J67*Assumption!$B$4 -> 200000 | I67: 10 | J67: =SUM(L67:W67) -> 200 | K67: 10 | T67: 50 | U67: 50 | V67: 50 | W67: 50 | X67: =SUM(Y67:AJ67) -> 220 | Y67: =ROUND(L67*(100+$K67)/100,0) -> 0 | Z67: 0 | AA67: =ROUND(N67*(100+$K67)/100,0) -> 0 | AB67: =ROUND(O67*(100+$K67)/100,0) -> 0 | AC67: =ROUND(P67*(100+$K67)/100,0) -> 0 | AD67: =ROUND(Q67*(100+$K67)/100,0) -> 0 | AE67: =ROUND(R67*(100+$K67)/100,0) -> 0 | AF67: =ROUND(S67*(100+$K67)/100,0) -> 0 | AG67: =ROUND(T67*(100+$K67)/100,0) -> 55 | AH67: =ROUND(U67*(100+$K67)/100,0) -> 55 | ... AJ67: =ROUND(W67*(100+$K67)/100,0) -> 55
A68: Midlands | B68: Midlands Connect - Rutland | C68: Midlands Connect - Rutland | D68: WPD_EM | E68: Midlands Connect - Rutland WP2 | F68: 60000 | G68: =J68*Assumption!$B$3 -> 100000 | H68: =J68*Assumption!$B$4 -> 100000 | I68: 10 | J68: =SUM(L68:W68) -> 100 | K68: 10 | V68: 50 | W68: 50 | X68: =SUM(Y68:AJ68) -> 110 | Y68: =ROUND(L68*(100+$K68)/100,0) -> 0 | Z68: 0 | AA68: =ROUND(N68*(100+$K68)/100,0) -> 0 | AB68: =ROUND(O68*(100+$K68)/100,0) -> 0 | AC68: =ROUND(P68*(100+$K68)/100,0) -> 0 | AD68: =ROUND(Q68*(100+$K68)/100,0) -> 0 | AE68: =ROUND(R68*(100+$K68)/100,0) -> 0 | AF68: =ROUND(S68*(100+$K68)/100,0) -> 0 | AG68: =ROUND(T68*(100+$K68)/100,0) -> 0 | AH68: =ROUND(U68*(100+$K68)/100,0) -> 0 | ... AJ68: =ROUND(W68*(100+$K68)/100,0) -> 55
A69: Midlands | B69: Midlands Connect - Warwickshire | C69: Midlands Connect - Warwickshire | D69: WPD_EM | E69: Midlands Connect - Warwickshire WP1 | F69: 165000 | G69: =J69*Assumption!$B$3 -> 200000 | H69: =J69*Assumption!$B$4 -> 200000 | I69: 10 | J69: =SUM(L69:W69) -> 200 | K69: 10 | T69: 50 | U69: 50 | V69: 50 | W69: 50 | X69: =SUM(Y69:AJ69) -> 220 | Y69: =ROUND(L69*(100+$K69)/100,0) -> 0 | Z69: 0 | AA69: =ROUND(N69*(100+$K69)/100,0) -> 0 | AB69: =ROUND(O69*(100+$K69)/100,0) -> 0 | AC69: =ROUND(P69*(100+$K69)/100,0) -> 0 | AD69: =ROUND(Q69*(100+$K69)/100,0) -> 0 | AE69: =ROUND(R69*(100+$K69)/100,0) -> 0 | AF69: =ROUND(S69*(100+$K69)/100,0) -> 0 | AG69: =ROUND(T69*(100+$K69)/100,0) -> 55 | AH69: =ROUND(U69*(100+$K69)/100,0) -> 55 | ... AJ69: =ROUND(W69*(100+$K69)/100,0) -> 55
A70: Midlands | B70: Midlands Connect - Warwickshire | C70: Midlands Connect - Warwickshire | D70: WPD_EM | E70: Midlands Connect - Warwickshire WP2 | F70: 0 | G70: =J70*Assumption!$B$3 -> 0 | H70: =J70*Assumption!$B$4 -> 0 | I70: 10 | J70: =SUM(L70:W70) -> 0 | K70: 10 | X70: =SUM(Y70:AJ70) -> 0 | Y70: =ROUND(L70*(100+$K70)/100,0) -> 0 | Z70: 0 | AA70: =ROUND(N70*(100+$K70)/100,0) -> 0 | AB70: =ROUND(O70*(100+$K70)/100,0) -> 0 | AC70: =ROUND(P70*(100+$K70)/100,0) -> 0 | AD70: =ROUND(Q70*(100+$K70)/100,0) -> 0 | AE70: =ROUND(R70*(100+$K70)/100,0) -> 0 | AF70: =ROUND(S70*(100+$K70)/100,0) -> 0 | AG70: =ROUND(T70*(100+$K70)/100,0) -> 0 | AH70: =ROUND(U70*(100+$K70)/100,0) -> 0 | ... AJ70: =ROUND(W70*(100+$K70)/100,0) -> 0
A71: Midlands | B71: Midlands Connect - Warwickshire | C71: Midlands Connect - Warwickshire | D71: WPD_EM | E71: Midlands Connect - Warwickshire WP3 | F71: 0 | G71: =J71*Assumption!$B$3 -> 0 | H71: =J71*Assumption!$B$4 -> 0 | I71: 10 | J71: =SUM(L71:W71) -> 0 | K71: 10 | X71: =SUM(Y71:AJ71) -> 0 | Y71: =ROUND(L71*(100+$K71)/100,0) -> 0 | Z71: 0 | AA71: =ROUND(N71*(100+$K71)/100,0) -> 0 | AB71: =ROUND(O71*(100+$K71)/100,0) -> 0 | AC71: =ROUND(P71*(100+$K71)/100,0) -> 0 | AD71: =ROUND(Q71*(100+$K71)/100,0) -> 0 | AE71: =ROUND(R71*(100+$K71)/100,0) -> 0 | AF71: =ROUND(S71*(100+$K71)/100,0) -> 0 | AG71: =ROUND(T71*(100+$K71)/100,0) -> 0 | AH71: =ROUND(U71*(100+$K71)/100,0) -> 0 | ... AJ71: =ROUND(W71*(100+$K71)/100,0) -> 0
A72: Midlands | B72: Midlands Connect - Warwickshire | C72: Midlands Connect - Warwickshire | D72: WPD_EM | E72: Midlands Connect - Warwickshire WP4 | F72: 0 | G72: =J72*Assumption!$B$3 -> 0 | H72: =J72*Assumption!$B$4 -> 0 | I72: 10 | J72: =SUM(L72:W72) -> 0 | K72: 10 | X72: =SUM(Y72:AJ72) -> 0 | Y72: =ROUND(L72*(100+$K72)/100,0) -> 0 | Z72: 0 | AA72: =ROUND(N72*(100+$K72)/100,0) -> 0 | AB72: =ROUND(O72*(100+$K72)/100,0) -> 0 | AC72: =ROUND(P72*(100+$K72)/100,0) -> 0 | AD72: =ROUND(Q72*(100+$K72)/100,0) -> 0 | AE72: =ROUND(R72*(100+$K72)/100,0) -> 0 | AF72: =ROUND(S72*(100+$K72)/100,0) -> 0 | AG72: =ROUND(T72*(100+$K72)/100,0) -> 0 | AH72: =ROUND(U72*(100+$K72)/100,0) -> 0 | ... AJ72: =ROUND(W72*(100+$K72)/100,0) -> 0
A73: Midlands | B73: Midlands Connect - Worcestershire | C73: Midlands Connect - Worcestershire | D73: WPD_EM | E73: Midlands Connect - Worcestershire WP1 | F73: 165000 | G73: =J73*Assumption!$B$3 -> 200000 | H73: =J73*Assumption!$B$4 -> 200000 | I73: 10 | J73: =SUM(L73:W73) -> 200 | K73: 10 | T73: 50 | U73: 50 | V73: 50 | W73: 50 | X73: =SUM(Y73:AJ73) -> 220 | Y73: =ROUND(L73*(100+$K73)/100,0) -> 0 | Z73: 0 | AA73: =ROUND(N73*(100+$K73)/100,0) -> 0 | AB73: =ROUND(O73*(100+$K73)/100,0) -> 0 | AC73: =ROUND(P73*(100+$K73)/100,0) -> 0 | AD73: =ROUND(Q73*(100+$K73)/100,0) -> 0 | AE73: =ROUND(R73*(100+$K73)/100,0) -> 0 | AF73: =ROUND(S73*(100+$K73)/100,0) -> 0 | AG73: =ROUND(T73*(100+$K73)/100,0) -> 55 | AH73: =ROUND(U73*(100+$K73)/100,0) -> 55 | ... AJ73: =ROUND(W73*(100+$K73)/100,0) -> 55
A74: Midlands | B74: Midlands Connect - Worcestershire | C74: Midlands Connect - Worcestershire | D74: WPD_EM | E74: Midlands Connect - Worcestershire WP2 | F74: 60000 | G74: =J74*Assumption!$B$3 -> 100000 | H74: =J74*Assumption!$B$4 -> 100000 | I74: 10 | J74: =SUM(L74:W74) -> 100 | K74: 10 | V74: 50 | W74: 50 | X74: =SUM(Y74:AJ74) -> 110 | Y74: =ROUND(L74*(100+$K74)/100,0) -> 0 | Z74: 0 | AA74: =ROUND(N74*(100+$K74)/100,0) -> 0 | AB74: =ROUND(O74*(100+$K74)/100,0) -> 0 | AC74: =ROUND(P74*(100+$K74)/100,0) -> 0 | AD74: =ROUND(Q74*(100+$K74)/100,0) -> 0 | AE74: =ROUND(R74*(100+$K74)/100,0) -> 0 | AF74: =ROUND(S74*(100+$K74)/100,0) -> 0 | AG74: =ROUND(T74*(100+$K74)/100,0) -> 0 | AH74: =ROUND(U74*(100+$K74)/100,0) -> 0 | ... AJ74: =ROUND(W74*(100+$K74)/100,0) -> 55
A75: Midlands | B75: Midlands Connect - Worcestershire | C75: Midlands Connect - Worcestershire | D75: WPD_EM | E75: Midlands Connect - Worcestershire WP3 | F75: 0 | G75: =J75*Assumption!$B$3 -> 0 | H75: =J75*Assumption!$B$4 -> 0 | I75: 10 | J75: =SUM(L75:W75) -> 0 | K75: 10 | X75: =SUM(Y75:AJ75) -> 0 | Y75: =ROUND(L75*(100+$K75)/100,0) -> 0 | Z75: 0 | AA75: =ROUND(N75*(100+$K75)/100,0) -> 0 | AB75: =ROUND(O75*(100+$K75)/100,0) -> 0 | AC75: =ROUND(P75*(100+$K75)/100,0) -> 0 | AD75: =ROUND(Q75*(100+$K75)/100,0) -> 0 | AE75: =ROUND(R75*(100+$K75)/100,0) -> 0 | AF75: =ROUND(S75*(100+$K75)/100,0) -> 0 | AG75: =ROUND(T75*(100+$K75)/100,0) -> 0 | AH75: =ROUND(U75*(100+$K75)/100,0) -> 0 | ... AJ75: =ROUND(W75*(100+$K75)/100,0) -> 0
A76: Midlands | B76: Midlands Connect - Trojan | C76: Midlands Connect - Trojan | D76: WPD_EM | E76: Trojan WPX | F76: 0 | G76: =J76*Assumption!$B$3 -> 0 | H76: =J76*Assumption!$B$4 -> 0 | I76: 10 | J76: =SUM(L76:W76) -> 0 | K76: 10 | X76: =SUM(Y76:AJ76) -> 0 | Y76: =ROUND(L76*(100+$K76)/100,0) -> 0 | Z76: 0 | AA76: =ROUND(N76*(100+$K76)/100,0) -> 0 | AB76: =ROUND(O76*(100+$K76)/100,0) -> 0 | AC76: =ROUND(P76*(100+$K76)/100,0) -> 0 | AD76: =ROUND(Q76*(100+$K76)/100,0) -> 0 | AE76: =ROUND(R76*(100+$K76)/100,0) -> 0 | AF76: =ROUND(S76*(100+$K76)/100,0) -> 0 | AG76: =ROUND(T76*(100+$K76)/100,0) -> 0 | AH76: =ROUND(U76*(100+$K76)/100,0) -> 0 | ... AJ76: =ROUND(W76*(100+$K76)/100,0) -> 0
A77: North | B77: Blackburn | C77: Blackburn | D77: SSEN_N | E77: Blackburn WP1 | F77: 150000 | G77: =J77*Assumption!$B$3 -> 150000 | H77: =J77*Assumption!$B$4 -> 150000 | I77: 10 | J77: =SUM(L77:W77) -> 150 | K77: 10 | Q77: 50 | R77: 50 | S77: 50 | X77: =SUM(Y77:AJ77) -> 165 | Y77: =ROUND(L77*(100+$K77)/100,0) -> 0 | Z77: 0 | AA77: =ROUND(N77*(100+$K77)/100,0) -> 0 | AB77: =ROUND(O77*(100+$K77)/100,0) -> 0 | AC77: =ROUND(P77*(100+$K77)/100,0) -> 0 | AD77: =ROUND(Q77*(100+$K77)/100,0) -> 55 | AE77: =ROUND(R77*(100+$K77)/100,0) -> 55 | AF77: =ROUND(S77*(100+$K77)/100,0) -> 55 | AG77: =ROUND(T77*(100+$K77)/100,0) -> 0 | AH77: =ROUND(U77*(100+$K77)/100,0) -> 0 | ... AJ77: =ROUND(W77*(100+$K77)/100,0) -> 0
A78: North | B78: Blackburn | C78: Blackburn | D78: SSEN_N | E78: Blackburn WP2 | F78: 132000 | G78: =J78*Assumption!$B$3 -> 150000 | H78: =J78*Assumption!$B$4 -> 150000 | I78: 10 | J78: =SUM(L78:W78) -> 150 | K78: 10 | Q78: 50 | R78: 50 | S78: 50 | X78: =SUM(Y78:AJ78) -> 165 | Y78: =ROUND(L78*(100+$K78)/100,0) -> 0 | Z78: 0 | AA78: =ROUND(N78*(100+$K78)/100,0) -> 0 | AB78: =ROUND(O78*(100+$K78)/100,0) -> 0 | AC78: =ROUND(P78*(100+$K78)/100,0) -> 0 | AD78: =ROUND(Q78*(100+$K78)/100,0) -> 55 | AE78: =ROUND(R78*(100+$K78)/100,0) -> 55 | AF78: =ROUND(S78*(100+$K78)/100,0) -> 55 | AG78: =ROUND(T78*(100+$K78)/100,0) -> 0 | AH78: =ROUND(U78*(100+$K78)/100,0) -> 0 | ... AJ78: =ROUND(W78*(100+$K78)/100,0) -> 0
A79: North | B79: Blackburn | C79: Blackburn | D79: SSEN_N | E79: Blackburn WP3 | F79: 168000 | G79: =J79*Assumption!$B$3 -> 100000 | H79: =J79*Assumption!$B$4 -> 100000 | I79: 10 | J79: =SUM(L79:W79) -> 100 | K79: 10 | U79: 50 | V79: 50 | X79: =SUM(Y79:AJ79) -> 110 | Y79: =ROUND(L79*(100+$K79)/100,0) -> 0 | Z79: 0 | AA79: =ROUND(N79*(100+$K79)/100,0) -> 0 | AB79: =ROUND(O79*(100+$K79)/100,0) -> 0 | AC79: =ROUND(P79*(100+$K79)/100,0) -> 0 | AD79: =ROUND(Q79*(100+$K79)/100,0) -> 0 | AE79: =ROUND(R79*(100+$K79)/100,0) -> 0 | AF79: =ROUND(S79*(100+$K79)/100,0) -> 0 | AG79: =ROUND(T79*(100+$K79)/100,0) -> 0 | AH79: =ROUND(U79*(100+$K79)/100,0) -> 55 | ... AJ79: =ROUND(W79*(100+$K79)/100,0) -> 0
A80: North | B80: Warrington (LEVI Pilot) | C80: Warrington (LEVI Pilot) | D80: SSEN_N | E80: Warrington | F80: 225000 | G80: =J80*Assumption!$B$3 -> 200000 | H80: =J80*Assumption!$B$4 -> 200000 | I80: 10 | J80: =SUM(L80:W80) -> 200 | K80: 10 | Q80: 50 | R80: 50 | S80: 50 | T80: 50 | X80: =SUM(Y80:AJ80) -> 220 | Y80: =ROUND(L80*(100+$K80)/100,0) -> 0 | Z80: 0 | AA80: =ROUND(N80*(100+$K80)/100,0) -> 0 | AB80: =ROUND(O80*(100+$K80)/100,0) -> 0 | AC80: =ROUND(P80*(100+$K80)/100,0) -> 0 | AD80: =ROUND(Q80*(100+$K80)/100,0) -> 55 | AE80: =ROUND(R80*(100+$K80)/100,0) -> 55 | AF80: =ROUND(S80*(100+$K80)/100,0) -> 55 | AG80: =ROUND(T80*(100+$K80)/100,0) -> 55 | AH80: =ROUND(U80*(100+$K80)/100,0) -> 0 | ... AJ80: =ROUND(W80*(100+$K80)/100,0) -> 0
A81: North | B81: Warrington (LEVI) | C81: Warrington (LEVI) | D81: SSEN_N | E81: Warrington (LEVI) WPX | F81: 0 | G81: =J81*Assumption!$B$3 -> 0 | H81: =J81*Assumption!$B$4 -> 0 | I81: 10 | J81: =SUM(L81:W81) -> 0 | K81: 10 | X81: =SUM(Y81:AJ81) -> 0 | Y81: =ROUND(L81*(100+$K81)/100,0) -> 0 | Z81: 0 | AA81: =ROUND(N81*(100+$K81)/100,0) -> 0 | AB81: =ROUND(O81*(100+$K81)/100,0) -> 0 | AC81: =ROUND(P81*(100+$K81)/100,0) -> 0 | AD81: =ROUND(Q81*(100+$K81)/100,0) -> 0 | AE81: =ROUND(R81*(100+$K81)/100,0) -> 0 | AF81: =ROUND(S81*(100+$K81)/100,0) -> 0 | AG81: =ROUND(T81*(100+$K81)/100,0) -> 0 | AH81: =ROUND(U81*(100+$K81)/100,0) -> 0 | ... AJ81: =ROUND(W81*(100+$K81)/100,0) -> 0
A82: North | B82: Cheshire West & Chester | C82: Cheshire West & Chester | D82: SSEN_N | E82: Cheshire West and Chester WP1 | F82: 60000 | G82: =J82*Assumption!$B$3 -> 100000 | H82: =J82*Assumption!$B$4 -> 100000 | I82: 10 | J82: =SUM(L82:W82) -> 100 | K82: 10 | V82: 50 | W82: 50 | X82: =SUM(Y82:AJ82) -> 110 | Y82: =ROUND(L82*(100+$K82)/100,0) -> 0 | Z82: 0 | AA82: =ROUND(N82*(100+$K82)/100,0) -> 0 | AB82: =ROUND(O82*(100+$K82)/100,0) -> 0 | AC82: =ROUND(P82*(100+$K82)/100,0) -> 0 | AD82: =ROUND(Q82*(100+$K82)/100,0) -> 0 | AE82: =ROUND(R82*(100+$K82)/100,0) -> 0 | AF82: =ROUND(S82*(100+$K82)/100,0) -> 0 | AG82: =ROUND(T82*(100+$K82)/100,0) -> 0 | AH82: =ROUND(U82*(100+$K82)/100,0) -> 0 | ... AJ82: =ROUND(W82*(100+$K82)/100,0) -> 55
A83: North | B83: Cheshire West & Chester | C83: Cheshire West & Chester | D83: SSEN_N | E83: Cheshire West and Chester WP2 | F83: 0 | G83: =J83*Assumption!$B$3 -> 0 | H83: =J83*Assumption!$B$4 -> 0 | I83: 10 | J83: =SUM(L83:W83) -> 0 | K83: 10 | X83: =SUM(Y83:AJ83) -> 0 | Y83: =ROUND(L83*(100+$K83)/100,0) -> 0 | Z83: 0 | AA83: =ROUND(N83*(100+$K83)/100,0) -> 0 | AB83: =ROUND(O83*(100+$K83)/100,0) -> 0 | AC83: =ROUND(P83*(100+$K83)/100,0) -> 0 | AD83: =ROUND(Q83*(100+$K83)/100,0) -> 0 | AE83: =ROUND(R83*(100+$K83)/100,0) -> 0 | AF83: =ROUND(S83*(100+$K83)/100,0) -> 0 | AG83: =ROUND(T83*(100+$K83)/100,0) -> 0 | AH83: =ROUND(U83*(100+$K83)/100,0) -> 0 | ... AJ83: =ROUND(W83*(100+$K83)/100,0) -> 0
A84: North | B84: Cheshire West & Chester | C84: Cheshire West & Chester | D84: SSEN_N | E84: Cheshire West and Chester WP3 | F84: 0 | G84: =J84*Assumption!$B$3 -> 0 | H84: =J84*Assumption!$B$4 -> 0 | I84: 10 | J84: =SUM(L84:W84) -> 0 | K84: 10 | X84: =SUM(Y84:AJ84) -> 0 | Y84: =ROUND(L84*(100+$K84)/100,0) -> 0 | Z84: 0 | AA84: =ROUND(N84*(100+$K84)/100,0) -> 0 | AB84: =ROUND(O84*(100+$K84)/100,0) -> 0 | AC84: =ROUND(P84*(100+$K84)/100,0) -> 0 | AD84: =ROUND(Q84*(100+$K84)/100,0) -> 0 | AE84: =ROUND(R84*(100+$K84)/100,0) -> 0 | AF84: =ROUND(S84*(100+$K84)/100,0) -> 0 | AG84: =ROUND(T84*(100+$K84)/100,0) -> 0 | AH84: =ROUND(U84*(100+$K84)/100,0) -> 0 | ... AJ84: =ROUND(W84*(100+$K84)/100,0) -> 0
A85: North | B85: NECA - Gateshead | C85: NECA - Gateshead | D85: SSEN_N | E85: NECA - Gateshead WPX | F85: 0 | G85: =J85*Assumption!$B$3 -> 0 | H85: =J85*Assumption!$B$4 -> 0 | I85: 10 | J85: =SUM(L85:W85) -> 0 | K85: 10 | X85: =SUM(Y85:AJ85) -> 0 | Y85: =ROUND(L85*(100+$K85)/100,0) -> 0 | Z85: 0 | AA85: =ROUND(N85*(100+$K85)/100,0) -> 0 | AB85: =ROUND(O85*(100+$K85)/100,0) -> 0 | AC85: =ROUND(P85*(100+$K85)/100,0) -> 0 | AD85: =ROUND(Q85*(100+$K85)/100,0) -> 0 | AE85: =ROUND(R85*(100+$K85)/100,0) -> 0 | AF85: =ROUND(S85*(100+$K85)/100,0) -> 0 | AG85: =ROUND(T85*(100+$K85)/100,0) -> 0 | AH85: =ROUND(U85*(100+$K85)/100,0) -> 0 | ... AJ85: =ROUND(W85*(100+$K85)/100,0) -> 0
A86: North | B86: NECA - Newcastle upon Tyne | C86: NECA - Newcastle upon Tyne | D86: SSEN_N | E86: NECA - Newcastle upon Tyne WPX | F86: 0 | G86: =J86*Assumption!$B$3 -> 0 | H86: =J86*Assumption!$B$4 -> 0 | I86: 10 | J86: =SUM(L86:W86) -> 0 | K86: 10 | X86: =SUM(Y86:AJ86) -> 0 | Y86: =ROUND(L86*(100+$K86)/100,0) -> 0 | Z86: 0 | AA86: =ROUND(N86*(100+$K86)/100,0) -> 0 | AB86: =ROUND(O86*(100+$K86)/100,0) -> 0 | AC86: =ROUND(P86*(100+$K86)/100,0) -> 0 | AD86: =ROUND(Q86*(100+$K86)/100,0) -> 0 | AE86: =ROUND(R86*(100+$K86)/100,0) -> 0 | AF86: =ROUND(S86*(100+$K86)/100,0) -> 0 | AG86: =ROUND(T86*(100+$K86)/100,0) -> 0 | AH86: =ROUND(U86*(100+$K86)/100,0) -> 0 | ... AJ86: =ROUND(W86*(100+$K86)/100,0) -> 0
A87: North | B87: NECA - North Tyneside | C87: NECA - North Tyneside | D87: SSEN_N | E87: NECA - North Tyneside WPX | F87: 0 | G87: =J87*Assumption!$B$3 -> 0 | H87: =J87*Assumption!$B$4 -> 0 | I87: 10 | J87: =SUM(L87:W87) -> 0 | K87: 10 | X87: =SUM(Y87:AJ87) -> 0 | Y87: =ROUND(L87*(100+$K87)/100,0) -> 0 | Z87: 0 | AA87: =ROUND(N87*(100+$K87)/100,0) -> 0 | AB87: =ROUND(O87*(100+$K87)/100,0) -> 0 | AC87: =ROUND(P87*(100+$K87)/100,0) -> 0 | AD87: =ROUND(Q87*(100+$K87)/100,0) -> 0 | AE87: =ROUND(R87*(100+$K87)/100,0) -> 0 | AF87: =ROUND(S87*(100+$K87)/100,0) -> 0 | AG87: =ROUND(T87*(100+$K87)/100,0) -> 0 | AH87: =ROUND(U87*(100+$K87)/100,0) -> 0 | ... AJ87: =ROUND(W87*(100+$K87)/100,0) -> 0
A88: North | B88: NECA - South Tyneside | C88: NECA - South Tyneside | D88: SSEN_N | E88: NECA - South Tyneside WPX | F88: 0 | G88: =J88*Assumption!$B$3 -> 0 | H88: =J88*Assumption!$B$4 -> 0 | I88: 10 | J88: =SUM(L88:W88) -> 0 | K88: 10 | X88: =SUM(Y88:AJ88) -> 0 | Y88: =ROUND(L88*(100+$K88)/100,0) -> 0 | Z88: 0 | AA88: =ROUND(N88*(100+$K88)/100,0) -> 0 | AB88: =ROUND(O88*(100+$K88)/100,0) -> 0 | AC88: =ROUND(P88*(100+$K88)/100,0) -> 0 | AD88: =ROUND(Q88*(100+$K88)/100,0) -> 0 | AE88: =ROUND(R88*(100+$K88)/100,0) -> 0 | AF88: =ROUND(S88*(100+$K88)/100,0) -> 0 | AG88: =ROUND(T88*(100+$K88)/100,0) -> 0 | AH88: =ROUND(U88*(100+$K88)/100,0) -> 0 | ... AJ88: =ROUND(W88*(100+$K88)/100,0) -> 0
A89: North | B89: NECA - Sunderland | C89: NECA - Sunderland | D89: SSEN_N | E89: NECA - Sunderland WPX | F89: 0 | G89: =J89*Assumption!$B$3 -> 0 | H89: =J89*Assumption!$B$4 -> 0 | I89: 10 | J89: =SUM(L89:W89) -> 0 | K89: 10 | X89: =SUM(Y89:AJ89) -> 0 | Y89: =ROUND(L89*(100+$K89)/100,0) -> 0 | Z89: 0 | AA89: =ROUND(N89*(100+$K89)/100,0) -> 0 | AB89: =ROUND(O89*(100+$K89)/100,0) -> 0 | AC89: =ROUND(P89*(100+$K89)/100,0) -> 0 | AD89: =ROUND(Q89*(100+$K89)/100,0) -> 0 | AE89: =ROUND(R89*(100+$K89)/100,0) -> 0 | AF89: =ROUND(S89*(100+$K89)/100,0) -> 0 | AG89: =ROUND(T89*(100+$K89)/100,0) -> 0 | AH89: =ROUND(U89*(100+$K89)/100,0) -> 0 | ... AJ89: =ROUND(W89*(100+$K89)/100,0) -> 0
A90: North | B90: NECA - Northumberland | C90: NECA - Northumberland | D90: SSEN_N | E90: NECA - Northumberland WPX | F90: 0 | G90: =J90*Assumption!$B$3 -> 0 | H90: =J90*Assumption!$B$4 -> 0 | I90: 10 | J90: =SUM(L90:W90) -> 0 | K90: 10 | X90: =SUM(Y90:AJ90) -> 0 | Y90: =ROUND(L90*(100+$K90)/100,0) -> 0 | Z90: 0 | AA90: =ROUND(N90*(100+$K90)/100,0) -> 0 | AB90: =ROUND(O90*(100+$K90)/100,0) -> 0 | AC90: =ROUND(P90*(100+$K90)/100,0) -> 0 | AD90: =ROUND(Q90*(100+$K90)/100,0) -> 0 | AE90: =ROUND(R90*(100+$K90)/100,0) -> 0 | AF90: =ROUND(S90*(100+$K90)/100,0) -> 0 | AG90: =ROUND(T90*(100+$K90)/100,0) -> 0 | AH90: =ROUND(U90*(100+$K90)/100,0) -> 0 | ... AJ90: =ROUND(W90*(100+$K90)/100,0) -> 0
A91: North | B91: Sunderland - LEVI | C91: Sunderland - LEVI | D91: SSEN_N | E91: Sunderland - LEVI | F91: 139500 | G91: =J91*Assumption!$B$3 -> 200000 | H91: =J91*Assumption!$B$4 -> 200000 | I91: 10 | J91: =SUM(L91:W91) -> 200 | K91: 10 | N91: 50 | O91: 50 | P91: 50 | Q91: 50 | X91: =SUM(Y91:AJ91) -> 220 | Y91: =ROUND(L91*(100+$K91)/100,0) -> 0 | Z91: 0 | AA91: =ROUND(N91*(100+$K91)/100,0) -> 55 | AB91: =ROUND(O91*(100+$K91)/100,0) -> 55 | AC91: =ROUND(P91*(100+$K91)/100,0) -> 55 | AD91: =ROUND(Q91*(100+$K91)/100,0) -> 55 | AE91: =ROUND(R91*(100+$K91)/100,0) -> 0 | AF91: =ROUND(S91*(100+$K91)/100,0) -> 0 | AG91: =ROUND(T91*(100+$K91)/100,0) -> 0 | AH91: =ROUND(U91*(100+$K91)/100,0) -> 0 | ... AJ91: =ROUND(W91*(100+$K91)/100,0) -> 0
A92: North | B92: South Tyneside - Rapids - Levelling-up Fund | C92: South Tyneside - Rapids - Levelling-up Fund | D92: SSEN_N | E92: South Tyneside - Rapids - Levelling-up Fund | F92: 12000 | G92: =J92*Assumption!$B$3 -> 300000 | H92: =J92*Assumption!$B$4 -> 300000 | I92: 10 | J92: =SUM(L92:W92) -> 300 | K92: 10 | L92: 50 | M92: 50 | N92: 50 | O92: 50 | P92: 50 | Q92: 50 | X92: =SUM(Y92:AJ92) -> 279 | Y92: =ROUND(L92*(100+$K92)/100,0) -> 55 | Z92: 4 | AA92: =ROUND(N92*(100+$K92)/100,0) -> 55 | AB92: =ROUND(O92*(100+$K92)/100,0) -> 55 | AC92: =ROUND(P92*(100+$K92)/100,0) -> 55 | AD92: =ROUND(Q92*(100+$K92)/100,0) -> 55 | AE92: =ROUND(R92*(100+$K92)/100,0) -> 0 | AF92: =ROUND(S92*(100+$K92)/100,0) -> 0 | AG92: =ROUND(T92*(100+$K92)/100,0) -> 0 | AH92: =ROUND(U92*(100+$K92)/100,0) -> 0 | ... AJ92: =ROUND(W92*(100+$K92)/100,0) -> 0
A93: North | B93: Westmorland and Furness Council | C93: Westmorland and Furness Council | D93: SSEN_N | E93: Westmorland and Furness Council | F93: 75000 | G93: =J93*Assumption!$B$3 -> 200000 | H93: =J93*Assumption!$B$4 -> 200000 | I93: 10 | J93: =SUM(L93:W93) -> 200 | K93: 10 | N93: 50 | O93: 50 | P93: 50 | Q93: 50 | X93: =SUM(Y93:AJ93) -> 220 | Y93: =ROUND(L93*(100+$K93)/100,0) -> 0 | Z93: 0 | AA93: =ROUND(N93*(100+$K93)/100,0) -> 55 | AB93: =ROUND(O93*(100+$K93)/100,0) -> 55 | AC93: =ROUND(P93*(100+$K93)/100,0) -> 55 | AD93: =ROUND(Q93*(100+$K93)/100,0) -> 55 | AE93: =ROUND(R93*(100+$K93)/100,0) -> 0 | AF93: =ROUND(S93*(100+$K93)/100,0) -> 0 | AG93: =ROUND(T93*(100+$K93)/100,0) -> 0 | AH93: =ROUND(U93*(100+$K93)/100,0) -> 0 | ... AJ93: =ROUND(W93*(100+$K93)/100,0) -> 0
A94: Commercial | B94: Barratts | C94: Barratts | D94: WPD_SM | E94: Barratts | F94: 57000 | G94: =J94*Assumption!$B$3 -> 50000 | H94: =J94*Assumption!$B$4 -> 50000 | I94: 10 | J94: =SUM(L94:W94) -> 50 | K94: 10 | L94: 50 | X94: =SUM(Y94:AJ94) -> 55 | Y94: =ROUND(L94*(100+$K94)/100,0) -> 55 | Z94: 0 | AA94: =ROUND(N94*(100+$K94)/100,0) -> 0 | AB94: =ROUND(O94*(100+$K94)/100,0) -> 0 | AC94: =ROUND(P94*(100+$K94)/100,0) -> 0 | AD94: =ROUND(Q94*(100+$K94)/100,0) -> 0 | AE94: =ROUND(R94*(100+$K94)/100,0) -> 0 | AF94: =ROUND(S94*(100+$K94)/100,0) -> 0 | AG94: =ROUND(T94*(100+$K94)/100,0) -> 0 | AH94: =ROUND(U94*(100+$K94)/100,0) -> 0 | ... AJ94: =ROUND(W94*(100+$K94)/100,0) -> 0
A95: Commercial | B95: Prologis | C95: Prologis | D95: WPD_SM | E95: Prologis | F95: 25500 | G95: =J95*Assumption!$B$3 -> 50000 | H95: =J95*Assumption!$B$4 -> 50000 | I95: 10 | J95: =SUM(L95:W95) -> 50 | K95: 10 | N95: 50 | X95: =SUM(Y95:AJ95) -> 55 | Y95: =ROUND(L95*(100+$K95)/100,0) -> 0 | Z95: 0 | AA95: =ROUND(N95*(100+$K95)/100,0) -> 55 | AB95: =ROUND(O95*(100+$K95)/100,0) -> 0 | AC95: =ROUND(P95*(100+$K95)/100,0) -> 0 | AD95: =ROUND(Q95*(100+$K95)/100,0) -> 0 | AE95: =ROUND(R95*(100+$K95)/100,0) -> 0 | AF95: =ROUND(S95*(100+$K95)/100,0) -> 0 | AG95: =ROUND(T95*(100+$K95)/100,0) -> 0 | AH95: =ROUND(U95*(100+$K95)/100,0) -> 0 | ... AJ95: =ROUND(W95*(100+$K95)/100,0) -> 0

Sheet Assumption
A1: Value per socket | B1: Assumption | C1: Notes
A2: capex_bom | B2: 1000 | C2: Bill of Materials
A3: capex_installation | B3: 1000 | C3: On‑site build cost
A4: capex_connection | B4: 1000 | C4: Getting power to site, include ICP (Independent Connection Provider) and DNO cost
A5: capex | B5: =SUM(B2:B4) -> 3000
A6: Asset Value | B6: 1000
B8: No. of sockets
A9: Senior Delivery Manager annual capacity | B9: 1000
A10: Delivery Manger annual capacity | B10: 500
