Workbook

Sheet Sheet1
A1: region_name | B1: contract_name | C1: work_package_name | D1: capex_bom_per_socket | E1: capex_installation_per_socket | F1: capex_connection_per_socket | G1: total_capex_per_socket | H1: target_sockets | I1: target_sockets_1 | J1: target_sockets_2 | K1: target_sockets_3 | L1: target_sockets_4 | M1: target_sockets_5 | N1: target_sockets_6 | O1: target_sockets_7 | P1: target_sockets_8 | Q1: target_sockets_9 | R1: target_sockets_10 | S1: target_sockets_11 | T1: target_sockets_12
A2: SOUTH | B2: Surrey | C2: Surrey WP10 | D2: =Assumption!$B$2 -> 1000 | E2: =Assumption!$B$3 -> 1000 | F2: =Assumption!$B$4 -> 1000 | G2: =SUM(D2:F2) -> 3000 | H2: =SUM(I2:T2) -> 150 | I2: 50 | J2: 50 | K2: 50
A3: SOUTH | B3: Surrey | C3: Surrey WP11 | D3: =Assumption!$B$2 -> 1000 | E3: =Assumption!$B$3 -> 1000 | F3: =Assumption!$B$4 -> 1000 | G3: =SUM(D3:F3) -> 3000 | H3: =SUM(I3:T3) -> 100 | M3: 50 | N3: 50
A4: SOUTH | B4: Surrey | C4: Surrey WP12 | D4: =Assumption!$B$2 -> 1000 | E4: =Assumption!$B$3 -> 1000 | F4: =Assumption!$B$4 -> 1000 | G4: =SUM(D4:F4) -> 3000 | H4: =SUM(I4:T4) -> 100 | N4: 50 | O4: 50
A5: SOUTH | B5: Surrey | C5: Surrey WP13 | D5: =Assumption!$B$2 -> 1000 | E5: =Assumption!$B$3 -> 1000 | F5: =Assumption!$B$4 -> 1000 | G5: =SUM(D5:F5) -> 3000 | H5: =SUM(I5:T5) -> 100 | O5: 50 | P5: 50
A6: SOUTH | B6: Surrey | C6: Surrey WP14 | D6: =Assumption!$B$2 -> 1000 | E6: =Assumption!$B$3 -> 1000 | F6: =Assumption!$B$4 -> 1000 | G6: =SUM(D6:F6) -> 3000 | H6: =SUM(I6:T6) -> 100 | P6: 50 | Q6: 50
A7: SOUTH | B7: Surrey | C7: Surrey WP15 | D7: =Assumption!$B$2 -> 1000 | E7: =Assumption!$B$3 -> 1000 | F7: =Assumption!$B$4 -> 1000 | G7: =SUM(D7:F7) -> 3000 | H7: =SUM(I7:T7) -> 100 | R7: 50 | S7: 50
A8: SOUTH | B8: Surrey | C8: Surrey WP16 | D8: =Assumption!$B$2 -> 1000 | E8: =Assumption!$B$3 -> 1000 | F8: =Assumption!$B$4 -> 1000 | G8: =SUM(D8:F8) -> 3000 | H8: =SUM(I8:T8) -> 50 | T8: 50
A9: SOUTH | B9: Surrey | C9: Surrey WP17 | D9: =Assumption!$B$2 -> 1000 | E9: =Assumption!$B$3 -> 1000 | F9: =Assumption!$B$4 -> 1000 | G9: =SUM(D9:F9) -> 3000 | H9: =SUM(I9:T9) -> 0
A10: SOUTH | B10: Surrey | C10: Surrey WP18 | D10: =Assumption!$B$2 -> 1000 | E10: =Assumption!$B$3 -> 1000 | F10: =Assumption!$B$4 -> 1000 | G10: =SUM(D10:F10) -> 3000 | H10: =SUM(I10:T10) -> 0
A11: SOUTH | B11: Surrey | C11: Surrey WP19 | D11: =Assumption!$B$2 -> 1000 | E11: =Assumption!$B$3 -> 1000 | F11: =Assumption!$B$4 -> 1000 | G11: =SUM(D11:F11) -> 3000 | H11: =SUM(I11:T11) -> 0
A12: SOUTH | B12: Surrey | C12: Surrey WP20 | D12: =Assumption!$B$2 -> 1000 | E12: =Assumption!$B$3 -> 1000 | F12: =Assumption!$B$4 -> 1000 | G12: =SUM(D12:F12) -> 3000 | H12: =SUM(I12:T12) -> 0
A13: SOUTH | B13: Surrey | C13: Surrey WP21 | D13: =Assumption!$B$2 -> 1000 | E13: =Assumption!$B$3 -> 1000 | F13: =Assumption!$B$4 -> 1000 | G13: =SUM(D13:F13) -> 3000 | H13: =SUM(I13:T13) -> 0
A14: SOUTH | B14: Surrey | C14: Surrey WP22 | D14: =Assumption!$B$2 -> 1000 | E14: =Assumption!$B$3 -> 1000 | F14: =Assumption!$B$4 -> 1000 | G14: =SUM(D14:F14) -> 3000 | H14: =SUM(I14:T14) -> 0
A15: SOUTH | B15: Surrey LP | C15: Surrey Lamppost WP1 | D15: =Assumption!$B$2 -> 1000 | E15: =Assumption!$B$3 -> 1000 | F15: =Assumption!$B$4 -> 1000 | G15: =SUM(D15:F15) -> 3000 | H15: =SUM(I15:T15) -> 100 | L15: 50 | M15: 50
A16: SOUTH | B16: Surrey LP | C16: Surrey Lamppost WP2 | D16: =Assumption!$B$2 -> 1000 | E16: =Assumption!$B$3 -> 1000 | F16: =Assumption!$B$4 -> 1000 | G16: =SUM(D16:F16) -> 3000 | H16: =SUM(I16:T16) -> 300 | N16: 50 | O16: 50 | P16: 50 | Q16: 50 | R16: 50 | S16: 50
A17: SOUTH | B17: Surrey LP | C17: Surrey Lamppost WP3 | D17: =Assumption!$B$2 -> 1000 | E17: =Assumption!$B$3 -> 1000 | F17: =Assumption!$B$4 -> 1000 | G17: =SUM(D17:F17) -> 3000 | H17: =SUM(I17:T17) -> 100 | N17: 50 | O17: 50
A18: SOUTH | B18: Surrey LP | C18: Surrey Lamppost WP4 | D18: =Assumption!$B$2 -> 1000 | E18: =Assumption!$B$3 -> 1000 | F18: =Assumption!$B$4 -> 1000 | G18: =SUM(D18:F18) -> 3000 | H18: =SUM(I18:T18) -> 100 | O18: 50 | P18: 50
A19: SOUTH | B19: Surrey LP | C19: Surrey Lamppost WP5 | D19: =Assumption!$B$2 -> 1000 | E19: =Assumption!$B$3 -> 1000 | F19: =Assumption!$B$4 -> 1000 | G19: =SUM(D19:F19) -> 3000 | H19: =SUM(I19:T19) -> 100 | P19: 50 | Q19: 50
A20: SOUTH | B20: Surrey LP | C20: Surrey Lamppost WP6 | D20: =Assumption!$B$2 -> 1000 | E20: =Assumption!$B$3 -> 1000 | F20: =Assumption!$B$4 -> 1000 | G20: =SUM(D20:F20) -> 3000 | H20: =SUM(I20:T20) -> 100 | Q20: 50 | R20: 50
A21: SOUTH | B21: Surrey LP | C21: Surrey Lamppost WP7 | D21: =Assumption!$B$2 -> 1000 | E21: =Assumption!$B$3 -> 1000 | F21: =Assumption!$B$4 -> 1000 | G21: =SUM(D21:F21) -> 3000 | H21: =SUM(I21:T21) -> 100 | R21: 50 | S21: 50
A22: SOUTH | B22: Surrey LP | C22: Surrey Lamppost WP8 | D22: =Assumption!$B$2 -> 1000 | E22: =Assumption!$B$3 -> 1000 | F22: =Assumption!$B$4 -> 1000 | G22: =SUM(D22:F22) -> 3000 | H22: =SUM(I22:T22) -> 100 | S22: 50 | T22: 50
A23: SOUTH | B23: Surrey LP | C23: Surrey Lamppost WP9 | D23: =Assumption!$B$2 -> 1000 | E23: =Assumption!$B$3 -> 1000 | F23: =Assumption!$B$4 -> 1000 | G23: =SUM(D23:F23) -> 3000 | H23: =SUM(I23:T23) -> 50 | T23: 50
A24: SOUTH | B24: Surrey LP | C24: Surrey Lamppost WP10 | D24: =Assumption!$B$2 -> 1000 | E24: =Assumption!$B$3 -> 1000 | F24: =Assumption!$B$4 -> 1000 | G24: =SUM(D24:F24) -> 3000 | H24: =SUM(I24:T24) -> 0
A25: SOUTH | B25: Surrey LP | C25: Surrey Lamppost WP11 | D25: =Assumption!$B$2 -> 1000 | E25: =Assumption!$B$3 -> 1000 | F25: =Assumption!$B$4 -> 1000 | G25: =SUM(D25:F25) -> 3000 | H25: =SUM(I25:T25) -> 0
A26: SOUTH | B26: Plymouth | C26: Plymouth WP1 | D26: =Assumption!$B$2 -> 1000 | E26: =Assumption!$B$3 -> 1000 | F26: =Assumption!$B$4 -> 1000 | G26: =SUM(D26:F26) -> 3000 | H26: =SUM(I26:T26) -> 50 | I26: 0 | J26: 0 | K26: 0 | L26: 50 | M26: 0 | N26: 0 | O26: 0 | P26: 0 | Q26: 0 | R26: 0 | S26: 0 | T26: 0
A27: SOUTH | B27: Plymouth | C27: Plymouth WP2 | D27: =Assumption!$B$2 -> 1000 | E27: =Assumption!$B$3 -> 1000 | F27: =Assumption!$B$4 -> 1000 | G27: =SUM(D27:F27) -> 3000 | H27: =SUM(I27:T27) -> 100 | I27: 0 | J27: 0 | K27: 0 | L27: 0 | M27: 50 | N27: 50 | O27: 0 | P27: 0 | Q27: 0 | R27: 0 | S27: 0 | T27: 0
A28: SOUTH | B28: Plymouth | C28: Plymouth WP3 | D28: =Assumption!$B$2 -> 1000 | E28: =Assumption!$B$3 -> 1000 | F28: =Assumption!$B$4 -> 1000 | G28: =SUM(D28:F28) -> 3000 | H28: =SUM(I28:T28) -> 150 | I28: 0 | J28: 0 | K28: 0 | L28: 0 | M28: 0 | N28: 0 | O28: 50 | P28: 50 | Q28: 50 | R28: 0 | S28: 0 | T28: 0
A29: SOUTH | B29: Plymouth | C29: Plymouth WP4 | D29: =Assumption!$B$2 -> 1000 | E29: =Assumption!$B$3 -> 1000 | F29: =Assumption!$B$4 -> 1000 | G29: =SUM(D29:F29) -> 3000 | H29: =SUM(I29:T29) -> 150 | I29: 0 | J29: 0 | K29: 0 | L29: 0 | M29: 0 | N29: 0 | O29: 0 | P29: 0 | Q29: 50 | R29: 50 | S29: 50 | T29: 0
A30: SOUTH | B30: Plymouth | C30: Plymouth WP5 | D30: =Assumption!$B$2 -> 1000 | E30: =Assumption!$B$3 -> 1000 | F30: =Assumption!$B$4 -> 1000 | G30: =SUM(D30:F30) -> 3000 | H30: =SUM(I30:T30) -> 50 | I30: 0 | J30: 0 | K30: 0 | L30: 0 | M30: 0 | N30: 0 | O30: 0 | P30: 0 | Q30: 0 | R30: 0 | S30: 0 | T30: 50
A31: SOUTH | B31: Bournemouth, Christchurch & Poole | C31: Bournemouth, Christchurch and Poole WP1 | D31: =Assumption!$B$2 -> 1000 | E31: =Assumption!$B$3 -> 1000 | F31: =Assumption!$B$4 -> 1000 | G31: =SUM(D31:F31) -> 3000 | H31: =SUM(I31:T31) -> 200 | Q31: 50 | R31: 50 | S31: 50 | T31: 50
A32: SOUTH | B32: Bournemouth, Christchurch & Poole | C32: Bournemouth, Christchurch and Poole WP2 | D32: =Assumption!$B$2 -> 1000 | E32: =Assumption!$B$3 -> 1000 | F32: =Assumption!$B$4 -> 1000 | G32: =SUM(D32:F32) -> 3000 | H32: =SUM(I32:T32) -> 0
A33: SOUTH | B33: Bournemouth, Christchurch & Poole | C33: Bournemouth, Christchurch and Poole WP3 | D33: =Assumption!$B$2 -> 1000 | E33: =Assumption!$B$3 -> 1000 | F33: =Assumption!$B$4 -> 1000 | G33: =SUM(D33:F33) -> 3000 | H33: =SUM(I33:T33) -> 0
A34: SOUTH | B34: Dorset | C34: Dorset WP1 | D34: =Assumption!$B$2 -> 1000 | E34: =Assumption!$B$3 -> 1000 | F34: =Assumption!$B$4 -> 1000 | G34: =SUM(D34:F34) -> 3000 | H34: =SUM(I34:T34) -> 200 | P34: 50 | Q34: 50 | R34: 50 | S34: 50
A35: SOUTH | B35: Dorset | C35: Dorset WP2 | D35: =Assumption!$B$2 -> 1000 | E35: =Assumption!$B$3 -> 1000 | F35: =Assumption!$B$4 -> 1000 | G35: =SUM(D35:F35) -> 3000 | H35: =SUM(I35:T35) -> 50 | T35: 50
A36: SOUTH | B36: Dorset | C36: Dorset WP3 | D36: =Assumption!$B$2 -> 1000 | E36: =Assumption!$B$3 -> 1000 | F36: =Assumption!$B$4 -> 1000 | G36: =SUM(D36:F36) -> 3000 | H36: =SUM(I36:T36) -> 0
A37: SOUTH | B37: West Sussex | C37: West Sussex - Phase 4 WP2 | D37: =Assumption!$B$2 -> 1000 | E37: =Assumption!$B$3 -> 1000 | F37: =Assumption!$B$4 -> 1000 | G37: =SUM(D37:F37) -> 3000 | H37: =SUM(I37:T37) -> 250 | I37: 50 | K37: 50 | O37: 50 | P37: 50 | Q37: 50
A38: SOUTH | B38: Wealden | C38: Wealden | D38: =Assumption!$B$2 -> 1000 | E38: =Assumption!$B$3 -> 1000 | F38: =Assumption!$B$4 -> 1000 | G38: =SUM(D38:F38) -> 3000 | H38: =SUM(I38:T38) -> 100 | I38: 50 | K38: 50
A39: SOUTH | B39: Havering | C39: Havering | D39: =Assumption!$B$2 -> 1000 | E39: =Assumption!$B$3 -> 1000 | F39: =Assumption!$B$4 -> 1000 | G39: =SUM(D39:F39) -> 3000 | H39: =SUM(I39:T39) -> 100 | J39: 50 | L39: 50
A40: SOUTH | B40: Dorset - LEVI Pilot WP1 | C40: Dorset - LEVI Pilot WP1 | D40: =Assumption!$B$2 -> 1000 | E40: =Assumption!$B$3 -> 1000 | F40: =Assumption!$B$4 -> 1000 | G40: =SUM(D40:F40) -> 3000 | H40: =SUM(I40:T40) -> 50 | O40: 50
A41: SOUTH | B41: Dorset - LEVI Pilot WP2 | C41: Dorset - LEVI Pilot WP2 | D41: =Assumption!$B$2 -> 1000 | E41: =Assumption!$B$3 -> 1000 | F41: =Assumption!$B$4 -> 1000 | G41: =SUM(D41:F41) -> 3000 | H41: =SUM(I41:T41) -> 0
A42: Central & Wales | B42: Windsor & Maidenhead | C42: Windsor & Maidenhead WPX | D42: =Assumption!$B$2 -> 1000 | E42: =Assumption!$B$3 -> 1000 | F42: =Assumption!$B$4 -> 1000 | G42: =SUM(D42:F42) -> 3000 | H42: =SUM(I42:T42) -> 0
A43: Central & Wales | B43: West Berkshire | C43: West Berkshire WP1 | D43: =Assumption!$B$2 -> 1000 | E43: =Assumption!$B$3 -> 1000 | F43: =Assumption!$B$4 -> 1000 | G43: =SUM(D43:F43) -> 3000 | H43: =SUM(I43:T43) -> 200 | M43: 50 | N43: 50 | O43: 50 | P43: 50
A44: Central & Wales | B44: West Berkshire | C44: West Berkshire WP2 | D44: =Assumption!$B$2 -> 1000 | E44: =Assumption!$B$3 -> 1000 | F44: =Assumption!$B$4 -> 1000 | G44: =SUM(D44:F44) -> 3000 | H44: =SUM(I44:T44) -> 200 | P44: 50 | Q44: 50 | R44: 50 | S44: 50
A45: Central & Wales | B45: West Berkshire | C45: West Berkshire WP3 | D45: =Assumption!$B$2 -> 1000 | E45: =Assumption!$B$3 -> 1000 | F45: =Assumption!$B$4 -> 1000 | G45: =SUM(D45:F45) -> 3000 | H45: =SUM(I45:T45) -> 50 | T45: 50
A46: Central & Wales | B46: North Northamptonshire | C46: North Northamptonshire WP1 | D46: =Assumption!$B$2 -> 1000 | E46: =Assumption!$B$3 -> 1000 | F46: =Assumption!$B$4 -> 1000 | G46: =SUM(D46:F46) -> 3000 | H46: =SUM(I46:T46) -> 200 | N46: 50 | O46: 50 | P46: 50 | Q46: 50
A47: Central & Wales | B47: North Northamptonshire | C47: North Northamptonshire WP2 | D47: =Assumption!$B$2 -> 1000 | E47: =Assumption!$B$3 -> 1000 | F47: =Assumption!$B$4 -> 1000 | G47: =SUM(D47:F47) -> 3000 | H47: =SUM(I47:T47) -> 200 | Q47: 50 | R47: 50 | S47: 50 | T47: 50
A48: Central & Wales | B48: North Northamptonshire | C48: North Northamptonshire WP3 | D48: =Assumption!$B$2 -> 1000 | E48: =Assumption!$B$3 -> 1000 | F48: =Assumption!$B$4 -> 1000 | G48: =SUM(D48:F48) -> 3000 | H48: =SUM(I48:T48) -> 0
A49: Central & Wales | B49: Oxfordshire | C49: Oxfordshire WP1 | D49: =Assumption!$B$2 -> 1000 | E49: =Assumption!$B$3 -> 1000 | F49: =Assumption!$B$4 -> 1000 | G49: =SUM(D49:F49) -> 3000 | H49: =SUM(I49:T49) -> 200 | M49: 50 | N49: 50 | O49: 50 | P49: 50
A50: Central & Wales | B50: Oxfordshire | C50: Oxfordshire WP2 | D50: =Assumption!$B$2 -> 1000 | E50: =Assumption!$B$3 -> 1000 | F50: =Assumption!$B$4 -> 1000 | G50: =SUM(D50:F50) -> 3000 | H50: =SUM(I50:T50) -> 200 | P50: 50 | Q50: 50 | R50: 50 | S50: 50
A51: Central & Wales | B51: Oxfordshire | C51: Oxfordshire WP3 | D51: =Assumption!$B$2 -> 1000 | E51: =Assumption!$B$3 -> 1000 | F51: =Assumption!$B$4 -> 1000 | G51: =SUM(D51:F51) -> 3000 | H51: =SUM(I51:T51) -> 50 | T51: 50
A52: Central & Wales | B52: Oxfordshire | C52: Oxfordshire WP4 | D52: =Assumption!$B$2 -> 1000 | E52: =Assumption!$B$3 -> 1000 | F52: =Assumption!$B$4 -> 1000 | G52: =SUM(D52:F52) -> 3000 | H52: =SUM(I52:T52) -> 0
A53: Central & Wales | B53: Oxfordshire | C53: Oxfordshire WP5 | D53: =Assumption!$B$2 -> 1000 | E53: =Assumption!$B$3 -> 1000 | F53: =Assumption!$B$4 -> 1000 | G53: =SUM(D53:F53) -> 3000 | H53: =SUM(I53:T53) -> 0
A54: Central & Wales | B54: Bedford | C54: Bedford WP1 | D54: =Assumption!$B$2 -> 1000 | E54: =Assumption!$B$3 -> 1000 | F54: =Assumption!$B$4 -> 1000 | G54: =SUM(D54:F54) -> 3000 | H54: =SUM(I54:T54) -> 150 | Q54: 50 | R54: 50 | S54: 50
A55: Central & Wales | B55: Bedford | C55: Bedford WP2 | D55: =Assumption!$B$2 -> 1000 | E55: =Assumption!$B$3 -> 1000 | F55: =Assumption!$B$4 -> 1000 | G55: =SUM(D55:F55) -> 3000 | H55: =SUM(I55:T55) -> 0
A56: Central & Wales | B56: Bedford | C56: Bedford WP3 | D56: =Assumption!$B$2 -> 1000 | E56: =Assumption!$B$3 -> 1000 | F56: =Assumption!$B$4 -> 1000 | G56: =SUM(D56:F56) -> 3000 | H56: =SUM(I56:T56) -> 0
A57: Central & Wales | B57: Gloucester - F&F | C57: Gloucester - F&F | D57: =Assumption!$B$2 -> 1000 | E57: =Assumption!$B$3 -> 1000 | F57: =Assumption!$B$4 -> 1000 | G57: =SUM(D57:F57) -> 3000 | H57: =SUM(I57:T57) -> 50 | K57: 50
A58: Central & Wales | B58: Gloucester - GCC LEVI WP3 | C58: Gloucester - GCC LEVI WP3 | D58: =Assumption!$B$2 -> 1000 | E58: =Assumption!$B$3 -> 1000 | F58: =Assumption!$B$4 -> 1000 | G58: =SUM(D58:F58) -> 3000 | H58: =SUM(I58:T58) -> 100 | J58: 50 | K58: 50
A59: Central & Wales | B59: CCR | C59: CCR | D59: =Assumption!$B$2 -> 1000 | E59: =Assumption!$B$3 -> 1000 | F59: =Assumption!$B$4 -> 1000 | G59: =SUM(D59:F59) -> 3000 | H59: =SUM(I59:T59) -> 50 | J59: 50
A60: Central & Wales | B60: Barking & Dagenham | C60: Barking & Dagenham | D60: =Assumption!$B$2 -> 1000 | E60: =Assumption!$B$3 -> 1000 | F60: =Assumption!$B$4 -> 1000 | G60: =SUM(D60:F60) -> 3000 | H60: =SUM(I60:T60) -> 50 | K60: 50
A61: Central & Wales | B61: Suffolk | C61: Suffolk | D61: =Assumption!$B$2 -> 1000 | E61: =Assumption!$B$3 -> 1000 | F61: =Assumption!$B$4 -> 1000 | G61: =SUM(D61:F61) -> 3000 | H61: =SUM(I61:T61) -> 50 | K61: 50
A62: Central & Wales | B62: Ceredigion | C62: Ceredigion | D62: =Assumption!$B$2 -> 1000 | E62: =Assumption!$B$3 -> 1000 | F62: =Assumption!$B$4 -> 1000 | G62: =SUM(D62:F62) -> 3000 | H62: =SUM(I62:T62) -> 100 | K62: 50 | L62: 50
A63: Midlands | B63: Midlands Connect - Leicestershire | C63: Midlands Connect - Leicestershire WP1 | D63: =Assumption!$B$2 -> 1000 | E63: =Assumption!$B$3 -> 1000 | F63: =Assumption!$B$4 -> 1000 | G63: =SUM(D63:F63) -> 3000 | H63: =SUM(I63:T63) -> 200 | Q63: 50 | R63: 50 | S63: 50 | T63: 50
A64: Midlands | B64: Midlands Connect - Leicestershire | C64: Midlands Connect - Leicestershire WP2 | D64: =Assumption!$B$2 -> 1000 | E64: =Assumption!$B$3 -> 1000 | F64: =Assumption!$B$4 -> 1000 | G64: =SUM(D64:F64) -> 3000 | H64: =SUM(I64:T64) -> 100 | S64: 50 | T64: 50
A65: Midlands | B65: Midlands Connect - Leicestershire | C65: Midlands Connect - Leicestershire WP3 | D65: =Assumption!$B$2 -> 1000 | E65: =Assumption!$B$3 -> 1000 | F65: =Assumption!$B$4 -> 1000 | G65: =SUM(D65:F65) -> 3000 | H65: =SUM(I65:T65) -> 0
A66: Midlands | B66: Midlands Connect - Leicestershire | C66: Midlands Connect - Leicestershire WP4 | D66: =Assumption!$B$2 -> 1000 | E66: =Assumption!$B$3 -> 1000 | F66: =Assumption!$B$4 -> 1000 | G66: =SUM(D66:F66) -> 3000 | H66: =SUM(I66:T66) -> 0
A67: Midlands | B67: Midlands Connect - Rutland | C67: Midlands Connect - Rutland WP1 | D67: =Assumption!$B$2 -> 1000 | E67: =Assumption!$B$3 -> 1000 | F67: =Assumption!$B$4 -> 1000 | G67: =SUM(D67:F67) -> 3000 | H67: =SUM(I67:T67) -> 200 | Q67: 50 | R67: 50 | S67: 50 | T67: 50
A68: Midlands | B68: Midlands Connect - Rutland | C68: Midlands Connect - Rutland WP2 | D68: =Assumption!$B$2 -> 1000 | E68: =Assumption!$B$3 -> 1000 | F68: =Assumption!$B$4 -> 1000 | G68: =SUM(D68:F68) -> 3000 | H68: =SUM(I68:T68) -> 100 | S68: 50 | T68: 50
A69: Midlands | B69: Midlands Connect - Warwickshire | C69: Midlands Connect - Warwickshire WP1 | D69: =Assumption!$B$2 -> 1000 | E69: =Assumption!$B$3 -> 1000 | F69: =Assumption!$B$4 -> 1000 | G69: =SUM(D69:F69) -> 3000 | H69: =SUM(I69:T69) -> 200 | Q69: 50 | R69: 50 | S69: 50 | T69: 50
A70: Midlands | B70: Midlands Connect - Warwickshire | C70: Midlands Connect - Warwickshire WP2 | D70: =Assumption!$B$2 -> 1000 | E70: =Assumption!$B$3 -> 1000 | F70: =Assumption!$B$4 -> 1000 | G70: =SUM(D70:F70) -> 3000 | H70: =SUM(I70:T70) -> 0
A71: Midlands | B71: Midlands Connect - Warwickshire | C71: Midlands Connect - Warwickshire WP3 | D71: =Assumption!$B$2 -> 1000 | E71: =Assumption!$B$3 -> 1000 | F71: =Assumption!$B$4 -> 1000 | G71: =SUM(D71:F71) -> 3000 | H71: =SUM(I71:T71) -> 0
A72: Midlands | B72: Midlands Connect - Warwickshire | C72: Midlands Connect - Warwickshire WP4 | D72: =Assumption!$B$2 -> 1000 | E72: =Assumption!$B$3 -> 1000 | F72: =Assumption!$B$4 -> 1000 | G72: =SUM(D72:F72) -> 3000 | H72: =SUM(I72:T72) -> 0
A73: Midlands | B73: Midlands Connect - Worcestershire | C73: Midlands Connect - Worcestershire WP1 | D73: =Assumption!$B$2 -> 1000 | E73: =Assumption!$B$3 -> 1000 | F73: =Assumption!$B$4 -> 1000 | G73: =SUM(D73:F73) -> 3000 | H73: =SUM(I73:T73) -> 200 | Q73: 50 | R73: 50 | S73: 50 | T73: 50
A74: Midlands | B74: Midlands Connect - Worcestershire | C74: Midlands Connect - Worcestershire WP2 | D74: =Assumption!$B$2 -> 1000 | E74: =Assumption!$B$3 -> 1000 | F74: =Assumption!$B$4 -> 1000 | G74: =SUM(D74:F74) -> 3000 | H74: =SUM(I74:T74) -> 100 | S74: 50 | T74: 50
A75: Midlands | B75: Midlands Connect - Worcestershire | C75: Midlands Connect - Worcestershire WP3 | D75: =Assumption!$B$2 -> 1000 | E75: =Assumption!$B$3 -> 1000 | F75: =Assumption!$B$4 -> 1000 | G75: =SUM(D75:F75) -> 3000 | H75: =SUM(I75:T75) -> 0
A76: Midlands | B76: Midlands Connect - Trojan | C76: Trojan WPX | D76: =Assumption!$B$2 -> 1000 | E76: =Assumption!$B$3 -> 1000 | F76: =Assumption!$B$4 -> 1000 | G76: =SUM(D76:F76) -> 3000 | H76: =SUM(I76:T76) -> 0
A77: North | B77: Blackburn | C77: Blackburn WP1 | D77: =Assumption!$B$2 -> 1000 | E77: =Assumption!$B$3 -> 1000 | F77: =Assumption!$B$4 -> 1000 | G77: =SUM(D77:F77) -> 3000 | H77: =SUM(I77:T77) -> 150 | N77: 50 | O77: 50 | P77: 50
A78: North | B78: Blackburn | C78: Blackburn WP2 | D78: =Assumption!$B$2 -> 1000 | E78: =Assumption!$B$3 -> 1000 | F78: =Assumption!$B$4 -> 1000 | G78: =SUM(D78:F78) -> 3000 | H78: =SUM(I78:T78) -> 150 | N78: 50 | O78: 50 | P78: 50
A79: North | B79: Blackburn | C79: Blackburn WP3 | D79: =Assumption!$B$2 -> 1000 | E79: =Assumption!$B$3 -> 1000 | F79: =Assumption!$B$4 -> 1000 | G79: =SUM(D79:F79) -> 3000 | H79: =SUM(I79:T79) -> 100 | R79: 50 | S79: 50
A80: North | B80: Warrington (LEVI Pilot) | C80: Warrington | D80: =Assumption!$B$2 -> 1000 | E80: =Assumption!$B$3 -> 1000 | F80: =Assumption!$B$4 -> 1000 | G80: =SUM(D80:F80) -> 3000 | H80: =SUM(I80:T80) -> 200 | N80: 50 | O80: 50 | P80: 50 | Q80: 50
A81: North | B81: Warrington (LEVI) | C81: Warrington (LEVI) WPX | D81: =Assumption!$B$2 -> 1000 | E81: =Assumption!$B$3 -> 1000 | F81: =Assumption!$B$4 -> 1000 | G81: =SUM(D81:F81) -> 3000 | H81: =SUM(I81:T81) -> 0
A82: North | B82: Cheshire West & Chester | C82: Cheshire West and Chester WP1 | D82: =Assumption!$B$2 -> 1000 | E82: =Assumption!$B$3 -> 1000 | F82: =Assumption!$B$4 -> 1000 | G82: =SUM(D82:F82) -> 3000 | H82: =SUM(I82:T82) -> 100 | S82: 50 | T82: 50
A83: North | B83: Cheshire West & Chester | C83: Cheshire West and Chester WP2 | D83: =Assumption!$B$2 -> 1000 | E83: =Assumption!$B$3 -> 1000 | F83: =Assumption!$B$4 -> 1000 | G83: =SUM(D83:F83) -> 3000 | H83: =SUM(I83:T83) -> 0
A84: North | B84: Cheshire West & Chester | C84: Cheshire West and Chester WP3 | D84: =Assumption!$B$2 -> 1000 | E84: =Assumption!$B$3 -> 1000 | F84: =Assumption!$B$4 -> 1000 | G84: =SUM(D84:F84) -> 3000 | H84: =SUM(I84:T84) -> 0
A85: North | B85: NECA - Gateshead | C85: NECA - Gateshead WPX | D85: =Assumption!$B$2 -> 1000 | E85: =Assumption!$B$3 -> 1000 | F85: =Assumption!$B$4 -> 1000 | G85: =SUM(D85:F85) -> 3000 | H85: =SUM(I85:T85) -> 0
A86: North | B86: NECA - Newcastle upon Tyne | C86: NECA - Newcastle upon Tyne WPX | D86: =Assumption!$B$2 -> 1000 | E86: =Assumption!$B$3 -> 1000 | F86: =Assumption!$B$4 -> 1000 | G86: =SUM(D86:F86) -> 3000 | H86: =SUM(I86:T86) -> 0
A87: North | B87: NECA - North Tyneside | C87: NECA - North Tyneside WPX | D87: =Assumption!$B$2 -> 1000 | E87: =Assumption!$B$3 -> 1000 | F87: =Assumption!$B$4 -> 1000 | G87: =SUM(D87:F87) -> 3000 | H87: =SUM(I87:T87) -> 0
A88: North | B88: NECA - South Tyneside | C88: NECA - South Tyneside WPX | D88: =Assumption!$B$2 -> 1000 | E88: =Assumption!$B$3 -> 1000 | F88: =Assumption!$B$4 -> 1000 | G88: =SUM(D88:F88) -> 3000 | H88: =SUM(I88:T88) -> 0
A89: North | B89: NECA - Sunderland | C89: NECA - Sunderland WPX | D89: =Assumption!$B$2 -> 1000 | E89: =Assumption!$B$3 -> 1000 | F89: =Assumption!$B$4 -> 1000 | G89: =SUM(D89:F89) -> 3000 | H89: =SUM(I89:T89) -> 0
A90: North | B90: NECA - Northumberland | C90: NECA - Northumberland WPX | D90: =Assumption!$B$2 -> 1000 | E90: =Assumption!$B$3 -> 1000 | F90: =Assumption!$B$4 -> 1000 | G90: =SUM(D90:F90) -> 3000 | H90: =SUM(I90:T90) -> 0
A91: North | B91: Sunderland - LEVI | C91: Sunderland - LEVI | D91: =Assumption!$B$2 -> 1000 | E91: =Assumption!$B$3 -> 1000 | F91: =Assumption!$B$4 -> 1000 | G91: =SUM(D91:F91) -> 3000 | H91: =SUM(I91:T91) -> 200 | K91: 50 | L91: 50 | M91: 50 | N91: 50
A92: North | B92: South Tyneside - Rapids - Levelling-up Fund | C92: South Tyneside - Rapids - Levelling-up Fund | D92: =Assumption!$B$2 -> 1000 | E92: =Assumption!$B$3 -> 1000 | F92: =Assumption!$B$4 -> 1000 | G92: =SUM(D92:F92) -> 3000 | H92: =SUM(I92:T92) -> 300 | I92: 50 | J92: 50 | K92: 50 | L92: 50 | M92: 50 | N92: 50
A93: North | B93: Westmorland and Furness Council | C93: Westmorland and Furness Council | D93: =Assumption!$B$2 -> 1000 | E93: =Assumption!$B$3 -> 1000 | F93: =Assumption!$B$4 -> 1000 | G93: =SUM(D93:F93) -> 3000 | H93: =SUM(I93:T93) -> 200 | K93: 50 | L93: 50 | M93: 50 | N93: 50
A94: Commercial | B94: Barratts | C94: Barratts | D94: =Assumption!$B$2 -> 1000 | E94: =Assumption!$B$3 -> 1000 | F94: =Assumption!$B$4 -> 1000 | G94: =SUM(D94:F94) -> 3000 | H94: =SUM(I94:T94) -> 50 | I94: 50
A95: Commercial | B95: Prologis | C95: Prologis | D95: =Assumption!$B$2 -> 1000 | E95: =Assumption!$B$3 -> 1000 | F95: =Assumption!$B$4 -> 1000 | G95: =SUM(D95:F95) -> 3000 | H95: =SUM(I95:T95) -> 50 | K95: 50

Sheet Capex Calculation
A1: BOM
A2: month 1 | B2: month 2 | C2: month 3 | D2: month 4 | E2: month 5 | F2: month 6 | G2: month 7 | H2: month 8 | I2: month 9 | J2: month 10 | K2: month 11 | L2: month 12

Sheet Assumption
A1: Value per socket | B1: Assumption | C1: Notes
A2: capex_bom | B2: 1000 | C2: Bill of Materials
A3: capex_installation | B3: 1000 | C3: On‑site build cost
A4: capex_connection | B4: 1000 | C4: Getting power to site, include ICP (Independent Connection Provider) and DNO cost
A5: capex | B5: =SUM(B2:B4) -> 3000
A6: Asset Value | B6: 1000
B8: No. of sockets
A9: Senior Delivery Manager annual capacity | B9: 1000
A10: Delivery Manger annual capacity | B10: 500
